[
  {
    "agent": "athome",
    "url": "https://www.athome.co.jp/tochi/1083086461/?DOWN=1&BKLISTID=001LPC&sref=list_simple",
    "title": "札幌市東区 北五十一条東６丁目 （太平駅 ） 住宅用地",
    "image": "https://www.athome.co.jp/image_files/path/no_image?width=320&height=320&margin=true",
    "price": 37000000,
    "nearStation": [
      {
        "name": "太平",
        "min": 1,
        "passenger": 0,
        "geometry": { "lng": 141.34926000000002, "lat": 43.123925 }
      }
    ],
    "access": "ＪＲ札沼線 「太平」駅 徒歩1分",
    "area": 262.8079,
    "prefecture": "sapporo",
    "info": { "buildingCoverageRatio": 60, "floorAreaRatio": 200 },
    "rentPrice": 45000
  },
  {
    "agent": "athome",
    "url": "https://www.athome.co.jp/tochi/1064649372/?DOWN=1&BKLISTID=001LPC&sref=list_simple",
    "title": "東大阪市 東石切町４丁目 （石切駅 ） 住宅用地",
    "image": "https://www.athome.co.jp/image_files/path/FrL9sOy3__w7mHiPHBBqZg==.jpeg?width=320&height=320&margin=true",
    "price": 39800000,
    "nearStation": [
      {
        "name": "石切",
        "min": 4,
        "passenger": 8887,
        "geometry": { "lng": 135.65461, "lat": 34.684245 }
      }
    ],
    "access": "近鉄奈良線 「石切」駅 徒歩4分",
    "area": 291.1788,
    "prefecture": "osaka",
    "info": { "buildingCoverageRatio": 60, "floorAreaRatio": 150 },
    "rentPrice": 59200
  },
  {
    "agent": "athome",
    "url": "https://www.athome.co.jp/tochi/1064647072/?DOWN=1&BKLISTID=001LPC&sref=list_simple",
    "title": "大阪市阿倍野区 阪南町１丁目 （昭和町駅 ） 住宅用地",
    "image": "https://www.athome.co.jp/image_files/path/seB8wmxHGcGYKUfOYMyfCQ==.jpeg?width=320&height=320&margin=true",
    "price": 36800000,
    "nearStation": [
      {
        "name": "昭和町",
        "min": 7,
        "passenger": 24311,
        "geometry": { "lng": 135.516885, "lat": 34.632975 }
      }
    ],
    "access": "地下鉄御堂筋線 「昭和町」駅 徒歩7分",
    "area": 104.1331,
    "prefecture": "osakaMetro",
    "info": { "buildingCoverageRatio": 60, "floorAreaRatio": 300 },
    "rentPrice": 53500
  },
  {
    "agent": "athome",
    "url": "https://www.athome.co.jp/tochi/6967660593/?DOWN=1&BKLISTID=001LPC&sref=list_simple",
    "title": "荒川区 東日暮里１丁目 （三ノ輪駅 ） 住宅用地",
    "image": "https://www.athome.co.jp/image_files/path/RhAQ6lPy3D6vsG1ZQIGpBw==.jpeg?width=320&height=320&margin=true",
    "price": 118000000,
    "nearStation": [
      {
        "name": "三ノ輪",
        "min": 5,
        "passenger": 43601,
        "geometry": { "lng": 139.791165, "lat": 35.729285000000004 }
      }
    ],
    "access": "東京メトロ日比谷線 「三ノ輪」駅 徒歩5分",
    "area": 116.0635,
    "prefecture": "tokyoMetro",
    "info": { "buildingCoverageRatio": 60, "floorAreaRatio": 300 },
    "rentPrice": 80421
  },
  {
    "agent": "athome",
    "url": "https://www.athome.co.jp/tochi/1023348639/?DOWN=1&BKLISTID=001LPC&sref=list_simple",
    "title": "目黒区 下目黒４丁目 （武蔵小山駅 ） 住宅用地",
    "image": "https://www.athome.co.jp/image_files/path/Sr29iEMx7AcOyLhN0yisng==.jpeg?width=320&height=320&margin=true",
    "price": 149800000,
    "nearStation": [
      {
        "name": "武蔵小山",
        "min": 13,
        "passenger": 53193,
        "geometry": { "lng": 139.70447000000001, "lat": 35.620509999999996 }
      }
    ],
    "access": "東急目黒線 「武蔵小山」駅 徒歩13分",
    "area": 108.3932,
    "prefecture": "tokyoMetro",
    "info": { "buildingCoverageRatio": 60, "floorAreaRatio": 200 },
    "rentPrice": 92403
  },
  {
    "agent": "athome",
    "url": "https://www.athome.co.jp/tochi/6976268483/?DOWN=1&BKLISTID=001LPC&sref=list_simple",
    "title": "日高市 四本木２丁目 （高麗川駅 ） 住宅用地",
    "image": "https://www.athome.co.jp/image_files/path/0qS2SchWwYEQQ6D7VM3Sgw==.jpeg?width=320&height=320&margin=true",
    "price": 15800000,
    "nearStation": [
      {
        "name": "高麗川",
        "min": 9,
        "passenger": 9160,
        "geometry": { "lng": 139.33813, "lat": 35.896370000000005 }
      }
    ],
    "access": "ＪＲ川越線 「高麗川」駅 徒歩9分",
    "area": 187.2656,
    "prefecture": "saitama",
    "info": { "buildingCoverageRatio": 60, "floorAreaRatio": 200 },
    "rentPrice": 52539
  },
  {
    "agent": "athome",
    "url": "https://www.athome.co.jp/tochi/1071192646/?DOWN=1&BKLISTID=001LPC&sref=list_simple",
    "title": "横浜市保土ケ谷区 霞台 （保土ケ谷駅 ） 住宅用地",
    "image": "https://www.athome.co.jp/image_files/path/cs7NA9CiiTSWUdjYlWDueA==.jpeg?width=320&height=320&margin=true",
    "price": 39800000,
    "nearStation": [
      {
        "name": "保土ケ谷",
        "min": 14,
        "passenger": 0,
        "geometry": { "lng": 0, "lat": 0 }
      }
    ],
    "access": "ＪＲ横須賀線 「保土ケ谷」駅 徒歩14分",
    "area": 256.6477,
    "prefecture": "kanagawaMetro",
    "info": { "buildingCoverageRatio": 50, "floorAreaRatio": 100 },
    "rentPrice": 50000
  },
  {
    "title": "鶴ヶ島市大字五味ヶ谷 (鶴ヶ島駅)",
    "agent": "homes",
    "area": 139.48,
    "price": 23000000,
    "info": { "buildingCoverageRatio": 60, "floorAreaRatio": 200 },
    "prefecture": "saitama",
    "image": "https://image.homes.jp/smallimg/image.php?file=http%3A%2F%2Fimg.homes.jp%2Fz9tm2rr6nhq15nt.jpg&width=208&height=138",
    "nearStation": [
      {
        "name": "鶴ヶ島",
        "min": 10,
        "passenger": 33139,
        "geometry": { "lng": 139.424355, "lat": 35.93651 }
      }
    ],
    "url": "https://www.homes.co.jp/tochi/b-1311270003018/",
    "access": "東武東上線 鶴ヶ島駅 徒歩10分",
    "rentPrice": 54217
  },
  {
    "area": 125.89,
    "price": 50000000,
    "width": 4,
    "title": "福岡県福岡市東区箱崎２丁目",
    "agent": "reins",
    "image": "",
    "prefecture": "fukuoka",
    "url": "https://system.reins.jp/login/main/KG/GKG001200",
    "info": { "floorAreaRatio": 160, "buildingCoverageRatio": 60 },
    "access": "福岡箱崎線　箱崎宮前 徒歩　5分",
    "nearStation": [
      {
        "name": "箱崎宮前",
        "min": 5,
        "passenger": 8935,
        "geometry": { "lng": 130.419365, "lat": 33.61608 }
      }
    ],
    "rentPrice": 41200
  },
  {
    "area": 289.75,
    "price": 145000000,
    "width": 4.3,
    "title": "宮城県仙台市青葉区柏木１丁目",
    "agent": "reins",
    "image": "",
    "prefecture": "sendai",
    "url": "https://system.reins.jp/login/main/KG/GKG001200",
    "info": { "floorAreaRatio": 258, "buildingCoverageRatio": 80 },
    "access": "仙台南北線　北四番丁 徒歩　8分",
    "nearStation": [
      {
        "name": "北四番丁",
        "min": 8,
        "passenger": 17154,
        "geometry": { "lng": 140.86910999999998, "lat": 38.272099999999995 }
      }
    ],
    "rentPrice": 64300
  },
  {
    "area": 166.8,
    "price": 29990000,
    "width": 9,
    "title": "京都府京都市右京区鳴滝本町",
    "agent": "reins",
    "image": "",
    "prefecture": "kyotoMetro",
    "url": "https://system.reins.jp/login/main/KG/GKG001200",
    "info": { "floorAreaRatio": 200, "buildingCoverageRatio": 60 },
    "access": "京福電鉄北野線　宇多野 徒歩　6分",
    "nearStation": [
      {
        "name": "宇多野",
        "min": 6,
        "passenger": 530,
        "geometry": { "lng": 135.70988, "lat": 35.027055000000004 }
      }
    ],
    "rentPrice": 45000
  },
  {
    "area": 160.35,
    "price": 89800000,
    "width": 11.9,
    "title": "神奈川県横浜市青葉区市ケ尾町",
    "agent": "reins",
    "image": "",
    "prefecture": "kanagawaMetro",
    "url": "https://system.reins.jp/login/main/KG/GKG001200",
    "info": { "floorAreaRatio": 200, "buildingCoverageRatio": 60 },
    "access": "田園都市線　市が尾 徒歩　6分",
    "nearStation": [
      {
        "name": "市が尾",
        "min": 6,
        "passenger": 43403,
        "geometry": { "lng": 139.54126, "lat": 35.551265 }
      }
    ],
    "rentPrice": 70760
  },
  {
    "area": 91.95,
    "price": 39900000,
    "width": 7.9,
    "title": "埼玉県さいたま市北区奈良町",
    "agent": "reins",
    "image": "",
    "prefecture": "saitama",
    "url": "https://system.reins.jp/login/main/KG/GKG001200",
    "info": { "floorAreaRatio": 200, "buildingCoverageRatio": 80 },
    "access": "高崎線　宮原 徒歩　10分",
    "nearStation": [
      {
        "name": "宮原",
        "min": 10,
        "passenger": 48558,
        "geometry": { "lng": 139.60952, "lat": 35.940529999999995 }
      }
    ],
    "rentPrice": 60127
  },
  {
    "title": "足立区江北２丁目土地",
    "image": "https://www.stepon.co.jp/pub/img/retail/11400D/120D1067/120D1067_m.jpg",
    "nearStation": [
      {
        "name": "江北",
        "min": 10,
        "passenger": 10912,
        "geometry": { "lng": 139.77034500000002, "lat": 35.773785000000004 }
      }
    ],
    "url": "https://www.stepon.co.jp/tochi/detail_120D1067/",
    "prefecture": "tokyoMetro",
    "agent": "stepon",
    "access": "日暮里舎人ライナー「江北」駅徒歩10分",
    "price": 58000000,
    "area": 162.73,
    "info": { "buildingCoverageRatio": 80, "floorAreaRatio": 300 },
    "rentPrice": 67241
  },
  {
    "agent": "athome",
    "url": "https://www.athome.co.jp/tochi/1083076461/?DOWN=1&BKLISTID=001LPC&sref=list_simple",
    "title": "堺市北区 金岡町 （新金岡駅 ） 住宅用地",
    "image": "https://www.athome.co.jp/image_files/path/2Z5qpTavd6YBk0cpVbI1ig==.jpeg?width=320&height=320&margin=true",
    "price": 48100000,
    "nearStation": [
      {
        "name": "新金岡",
        "min": 7,
        "passenger": 21512,
        "geometry": { "lng": 135.51527, "lat": 34.568200000000004 }
      }
    ],
    "access": "地下鉄御堂筋線 「新金岡」駅 徒歩7分",
    "area": 131.8239,
    "prefecture": "osaka",
    "info": { "buildingCoverageRatio": 60, "floorAreaRatio": 200 },
    "rentPrice": 51000
  },
  {
    "agent": "athome",
    "url": "https://www.athome.co.jp/tochi/1054719569/?DOWN=1&BKLISTID=001LPC&sref=list_simple",
    "title": "品川区 豊町４丁目 （戸越公園駅 ） 住宅用地",
    "image": "https://www.athome.co.jp/image_files/path/7b55ytNHxCY0wZf8i6EbyA==.jpeg?width=320&height=320&margin=true",
    "price": 99800000,
    "nearStation": [
      {
        "name": "戸越公園",
        "min": 6,
        "passenger": 13681,
        "geometry": { "lng": 139.71839, "lat": 35.60893 }
      }
    ],
    "access": "東急大井町線 「戸越公園」駅 徒歩6分",
    "area": 112.0333,
    "prefecture": "tokyoMetro",
    "info": { "buildingCoverageRatio": 60, "floorAreaRatio": 300 },
    "rentPrice": 87173
  },
  {
    "agent": "athome",
    "url": "https://www.athome.co.jp/tochi/1033338871/?DOWN=1&BKLISTID=001LPC&sref=list_simple",
    "title": "川口市 本町１丁目 （川口元郷駅 ） 住宅用地",
    "image": "https://www.athome.co.jp/image_files/path/-rMhiL_ICvBVUlZYTHqzbA==.jpeg?width=320&height=320&margin=true",
    "price": 64000000,
    "nearStation": [
      {
        "name": "川口元郷",
        "min": 9,
        "passenger": 20800,
        "geometry": { "lng": 139.72954499999997, "lat": 35.799620000000004 }
      }
    ],
    "access": "埼玉高速鉄道 「川口元郷」駅 徒歩9分",
    "area": 100.053,
    "prefecture": "saitama",
    "info": { "buildingCoverageRatio": 90, "floorAreaRatio": 400 },
    "rentPrice": 71554
  },
  {
    "agent": "athome",
    "url": "https://www.athome.co.jp/tochi/1081574761/?DOWN=1&BKLISTID=001LPC&sref=list_simple",
    "title": "坂戸市 緑町 （坂戸駅 ） 住宅用地",
    "image": "https://www.athome.co.jp/image_files/path/XjcKCqQKZ02xaPB9AeDBhg==.jpeg?width=320&height=320&margin=true",
    "price": 67900000,
    "nearStation": [
      {
        "name": "坂戸",
        "min": 4,
        "passenger": 29107,
        "geometry": { "lng": 139.394315, "lat": 35.957255 }
      }
    ],
    "access": "東武東上線 「坂戸」駅 徒歩4分",
    "area": 393.97119,
    "prefecture": "saitama",
    "info": { "buildingCoverageRatio": 60, "floorAreaRatio": 200 },
    "rentPrice": 55669
  },
  {
    "agent": "athome",
    "url": "https://www.athome.co.jp/tochi/6978923395/?DOWN=1&BKLISTID=001LPC&sref=list_simple",
    "title": "さいたま市南区 白幡２丁目 （武蔵浦和駅 ） 住宅用地",
    "image": "https://www.athome.co.jp/image_files/path/FWAaXj1a0yfdO2Eq5Hj9nw==.jpeg?width=320&height=320&margin=true",
    "price": 79000000,
    "nearStation": [
      {
        "name": "武蔵浦和",
        "min": 10,
        "passenger": 107926,
        "geometry": { "lng": 139.647935, "lat": 35.846045000000004 }
      }
    ],
    "access": "ＪＲ埼京線 「武蔵浦和」駅 徒歩10分",
    "area": 240.5772,
    "prefecture": "saitama",
    "info": { "buildingCoverageRatio": 60, "floorAreaRatio": 160 },
    "rentPrice": 68066
  },
  {
    "agent": "athome",
    "url": "https://www.athome.co.jp/tochi/1067838746/?DOWN=1&BKLISTID=001LPC&sref=list_simple",
    "title": "船橋市 二和東６丁目 （二和向台駅 ） 住宅用地",
    "image": "https://www.athome.co.jp/image_files/path/7mqG7KiAwDMEJCpAhxN6EQ==.jpeg?width=320&height=320&margin=true",
    "price": 28800000,
    "nearStation": [
      {
        "name": "二和向台",
        "min": 6,
        "passenger": 17446,
        "geometry": { "lng": 140.02373, "lat": 35.753885 }
      }
    ],
    "access": "新京成線 「二和向台」駅 徒歩6分",
    "area": 130.2339,
    "prefecture": "chiba",
    "info": { "buildingCoverageRatio": 60, "floorAreaRatio": 200 },
    "rentPrice": 51997
  },
  {
    "area": 363.63,
    "price": 132000000,
    "width": 8,
    "title": "北海道札幌市西区二十四軒一条６丁目",
    "agent": "reins",
    "image": "",
    "prefecture": "sapporo",
    "url": "https://system.reins.jp/login/main/KG/GKG001200",
    "info": { "floorAreaRatio": 200, "buildingCoverageRatio": 60 },
    "access": "地下東西線　二十四軒 徒歩　4分",
    "nearStation": [
      {
        "name": "二十四軒",
        "min": 4,
        "passenger": 13028,
        "geometry": { "lng": 141.313605, "lat": 43.07045 }
      }
    ],
    "rentPrice": 35600
  },
  {
    "area": 133.61,
    "price": 80000000,
    "width": 6.7,
    "title": "東京都町田市玉川学園７丁目",
    "agent": "reins",
    "image": "",
    "prefecture": "tokyo",
    "url": "https://system.reins.jp/login/main/KG/GKG001200",
    "info": { "floorAreaRatio": 200, "buildingCoverageRatio": 90 },
    "access": "小田急線　玉川学園前 徒歩　2分",
    "nearStation": [
      {
        "name": "玉川学園前",
        "min": 2,
        "passenger": 46581,
        "geometry": { "lng": 139.46344, "lat": 35.563509999999994 }
      }
    ],
    "rentPrice": 64782
  },
  {
    "area": 289.12,
    "price": 105000000,
    "width": 4,
    "title": "神奈川県相模原市緑区橋本６丁目",
    "agent": "reins",
    "image": "",
    "prefecture": "kanagawa",
    "url": "https://system.reins.jp/login/main/KG/GKG001200",
    "info": { "floorAreaRatio": 160, "buildingCoverageRatio": 70 },
    "access": "横浜線　橋本 徒歩　8分",
    "nearStation": [
      {
        "name": "橋本",
        "min": 8,
        "passenger": 230358,
        "geometry": { "lng": 139.34447, "lat": 35.595169999999996 }
      }
    ],
    "rentPrice": 66710
  },
  {
    "area": 158,
    "price": 72500000,
    "width": 4,
    "title": "神奈川県相模原市南区相模大野９丁目",
    "agent": "reins",
    "image": "",
    "prefecture": "kanagawa",
    "url": "https://system.reins.jp/login/main/KG/GKG001200",
    "info": { "floorAreaRatio": 160, "buildingCoverageRatio": 60 },
    "access": "小田急線　相模大野 徒歩　10分",
    "nearStation": [
      {
        "name": "相模大野",
        "min": 10,
        "passenger": 127169,
        "geometry": { "lng": 139.437265, "lat": 35.531670000000005 }
      }
    ],
    "rentPrice": 65207
  },
  {
    "title": "東京都板橋区成増５",
    "url": "https://suumo.jp/tochi/__JJ_JJ010FJ100_arz1030z2bsz1030z2ncz171791420.html",
    "image": "https://img01.suumo.com/jj/resizeImage?src=gazo%2Fbukken%2F030%2FN010000%2Fimg%2F420%2F71791420%2F71791420_0001.jpg&w=132&h=99",
    "agent": "suumo",
    "prefecture": "tokyoMetro",
    "area": 165.04,
    "price": 77800000,
    "access": "東武東上線「成増」徒歩13分",
    "nearStation": [
      {
        "name": "成増",
        "min": 13,
        "passenger": 58587,
        "geometry": { "lng": 139.63338, "lat": 35.777280000000005 }
      }
    ],
    "info": { "buildingCoverageRatio": 60, "floorAreaRatio": 200 },
    "rentPrice": 77802
  },
  {
    "title": "千葉県松戸市六実５",
    "url": "https://suumo.jp/tochi/__JJ_JJ010FJ100_arz1030z2bsz1030z2ncz172136446.html",
    "image": "https://img01.suumo.com/jj/resizeImage?src=gazo%2Fbukken%2F030%2FN010000%2Fimg%2F446%2F72136446%2F72136446_0002.jpg&w=132&h=99",
    "agent": "suumo",
    "prefecture": "chiba",
    "area": 148.76,
    "price": 16800000,
    "access": "東武野田線「六実」徒歩4分",
    "nearStation": [
      {
        "name": "六実",
        "min": 4,
        "passenger": 14840,
        "geometry": { "lng": 139.99924499999997, "lat": 35.793705 }
      }
    ],
    "info": { "buildingCoverageRatio": 60, "floorAreaRatio": 200 },
    "rentPrice": 52470
  },
  {
    "title": "兵庫県西宮市甲子園網引町",
    "url": "https://suumo.jp/tochi/__JJ_JJ010FJ100_arz1060z2bsz1030z2ncz170906441.html",
    "image": "https://img01.suumo.com/jj/resizeImage?src=gazo%2Fbukken%2F060%2FN010000%2Fimg%2F441%2F70906441%2F70906441_0048.jpg&w=132&h=99",
    "agent": "suumo",
    "prefecture": "hyogo",
    "area": 119.98,
    "price": 38900000,
    "access": "阪神本線「甲子園」徒歩11分",
    "nearStation": [
      {
        "name": "甲子園",
        "min": 11,
        "passenger": 54968,
        "geometry": { "lng": 135.363275, "lat": 34.723960000000005 }
      }
    ],
    "info": { "buildingCoverageRatio": 60, "floorAreaRatio": 200 },
    "rentPrice": 61500
  },
  {
    "title": "大阪府枚方市藤阪東町１",
    "url": "https://suumo.jp/tochi/__JJ_JJ010FJ100_arz1060z2bsz1030z2ncz172175893.html",
    "image": "https://img01.suumo.com/jj/resizeImage?src=gazo%2Fbukken%2F060%2FN010000%2Fimg%2F893%2F72175893%2F72175893_0032.jpg&w=132&h=99",
    "agent": "suumo",
    "prefecture": "osaka",
    "area": 121.01,
    "price": 22800000,
    "access": "ＪＲ片町線「長尾」徒歩10分",
    "nearStation": [
      {
        "name": "長尾",
        "min": 10,
        "passenger": 22888,
        "geometry": { "lng": 135.71321, "lat": 34.826065 }
      }
    ],
    "info": { "buildingCoverageRatio": 60, "floorAreaRatio": 200 },
    "rentPrice": 47700
  },
  {
    "title": "大阪府堺市北区百舌鳥梅町１",
    "url": "https://suumo.jp/tochi/__JJ_JJ010FJ100_arz1060z2bsz1030z2ncz172175545.html",
    "image": "https://img01.suumo.com/jj/resizeImage?src=gazo%2Fbukken%2F060%2FN010000%2Fimg%2F545%2F72175545%2F72175545_0007.jpg&w=132&h=99",
    "agent": "suumo",
    "prefecture": "osaka",
    "area": 103.6,
    "price": 36800000,
    "access": "南海高野線「中百舌鳥」徒歩9分",
    "nearStation": [
      {
        "name": "中百舌鳥",
        "min": 9,
        "passenger": 100593,
        "geometry": { "lng": 135.50428, "lat": 34.556235 }
      }
    ],
    "info": { "buildingCoverageRatio": 80, "floorAreaRatio": 300 },
    "rentPrice": 52600
  },
  {
    "title": "埼玉県川口市本町１",
    "url": "https://suumo.jp/tochi/__JJ_JJ010FJ100_arz1030z2bsz1030z2ncz171374336.html",
    "image": "https://img01.suumo.com/jj/resizeImage?src=gazo%2Fbukken%2F030%2FN010000%2Fimg%2F336%2F71374336%2F71374336_0005.jpg&w=132&h=99",
    "agent": "suumo",
    "prefecture": "saitama",
    "area": 100.05,
    "price": 64000000,
    "access": "ＪＲ京浜東北線「川口」徒歩15分",
    "nearStation": [
      {
        "name": "川口",
        "min": 15,
        "passenger": 169062,
        "geometry": { "lng": 139.717905, "lat": 35.800985 }
      }
    ],
    "info": { "buildingCoverageRatio": 90, "floorAreaRatio": 400 },
    "rentPrice": 75671
  },
  {
    "title": "兵庫県神戸市東灘区西岡本３",
    "url": "https://suumo.jp/tochi/__JJ_JJ010FJ100_arz1060z2bsz1030z2ncz170309262.html",
    "image": "https://img01.suumo.com/jj/resizeImage?src=gazo%2Fbukken%2F060%2FN010000%2Fimg%2F262%2F70309262%2F70309262_0014.jpg&w=132&h=99",
    "agent": "suumo",
    "prefecture": "hyogoMetro",
    "area": 137.3,
    "price": 44800000,
    "access": "ＪＲ東海道本線「摂津本山」徒歩11分",
    "nearStation": [
      {
        "name": "摂津本山",
        "min": 11,
        "passenger": 44056,
        "geometry": { "lng": 135.27757, "lat": 34.726805 }
      }
    ],
    "info": { "buildingCoverageRatio": 60, "floorAreaRatio": 150 },
    "rentPrice": 59500
  },
  {
    "title": "北海道札幌市白石区本郷通５丁目南",
    "url": "https://suumo.jp/tochi/__JJ_JJ010FJ100_arz1010z2bsz1030z2ncz170820161.html",
    "image": "https://img01.suumo.com/jj/resizeImage?src=gazo%2Fbukken%2F010%2FN010000%2Fimg%2F161%2F70820161%2F70820161_0001.jpg&w=132&h=99",
    "agent": "suumo",
    "prefecture": "sapporo",
    "area": 279.68,
    "price": 59800000,
    "access": "地下鉄東西線「南郷７丁目」徒歩7分",
    "nearStation": [
      {
        "name": "南郷７丁目",
        "min": 7,
        "passenger": 0,
        "geometry": { "lng": 0, "lat": 0 }
      }
    ],
    "info": { "buildingCoverageRatio": 60, "floorAreaRatio": 200 },
    "rentPrice": 45000
  },
  {
    "title": "北海道札幌市手稲区手稲本町三条２-2-1",
    "url": "https://suumo.jp/tochi/__JJ_JJ010FJ100_arz1010z2bsz1030z2ncz172176931.html",
    "image": "https://img01.suumo.com/jj/resizeImage?src=gazo%2Fbukken%2F010%2FN010000%2Fimg%2F931%2F72176931%2F72176931_0001.jpg&w=132&h=99",
    "agent": "suumo",
    "prefecture": "sapporo",
    "area": 462.33,
    "price": 63200000,
    "access": "ＪＲ函館本線「手稲」徒歩8分",
    "nearStation": [
      {
        "name": "手稲",
        "min": 8,
        "passenger": 30546,
        "geometry": { "lng": 141.24385, "lat": 43.120125 }
      }
    ],
    "info": { "buildingCoverageRatio": 60, "floorAreaRatio": 200 },
    "rentPrice": 41000
  },
  {
    "agent": "athome",
    "url": "https://www.athome.co.jp/tochi/6978477821/?DOWN=1&BKLISTID=001LPC&sref=list_simple",
    "title": "足立区 千住仲町 （北千住駅 ） 住宅用地",
    "image": "https://www.athome.co.jp/image_files/path/7Phxg4L62gU28mv_Devo3A==.jpeg?width=320&height=320&margin=true",
    "price": 56800000,
    "nearStation": [
      {
        "name": "北千住",
        "min": 4,
        "passenger": 1294209,
        "geometry": { "lng": 139.805235, "lat": 35.748725 }
      }
    ],
    "access": "東京メトロ千代田線 「北千住」駅 徒歩4分",
    "area": 92.1327,
    "prefecture": "tokyoMetro",
    "info": { "buildingCoverageRatio": 90, "floorAreaRatio": 300 },
    "rentPrice": 77645
  },
  {
    "agent": "athome",
    "url": "https://www.athome.co.jp/tochi/1000301181/?DOWN=1&BKLISTID=001LPC&sref=list_simple",
    "title": "比企郡滑川町 大字羽尾 （森林公園駅 ） 住宅用地",
    "image": "https://www.athome.co.jp/image_files/path/ZebjvMrh2-W9g2gIi5p_zA==.jpeg?width=320&height=320&margin=true",
    "price": 19800000,
    "nearStation": [
      {
        "name": "森林公園",
        "min": 3,
        "passenger": 14284,
        "geometry": { "lng": 139.37533000000002, "lat": 36.045165 }
      }
    ],
    "access": "東武東上線 「森林公園」駅 徒歩3分",
    "area": 248.1975,
    "prefecture": "saitama",
    "info": { "buildingCoverageRatio": 60, "floorAreaRatio": 200 },
    "rentPrice": 53483
  },
  {
    "agent": "athome",
    "url": "https://www.athome.co.jp/tochi/1083100674/?DOWN=1&BKLISTID=001LPC&sref=list_simple",
    "title": "狭山市 大字南入曽 （入曽駅 ） 住宅用地",
    "image": "https://www.athome.co.jp/image_files/path/w3Ac8v5dAE2cQWp4afryLA==.jpeg?width=320&height=320&margin=true",
    "price": 35800000,
    "nearStation": [
      {
        "name": "入曽",
        "min": 2,
        "passenger": 17764,
        "geometry": { "lng": 139.427185, "lat": 35.832385 }
      }
    ],
    "access": "西武新宿線 「入曽」駅 徒歩2分",
    "area": 116.3735,
    "prefecture": "saitama",
    "info": { "buildingCoverageRatio": 80, "floorAreaRatio": 400 },
    "rentPrice": 54077
  },
  {
    "area": 166.48,
    "price": 25900000,
    "width": 4,
    "title": "宮城県仙台市青葉区旭ケ丘１丁目",
    "agent": "reins",
    "image": "",
    "prefecture": "sendai",
    "url": "https://system.reins.jp/login/main/KG/GKG001200",
    "info": { "floorAreaRatio": 160, "buildingCoverageRatio": 70 },
    "access": "仙台南北線　台原 徒歩　8分",
    "nearStation": [
      {
        "name": "台原",
        "min": 8,
        "passenger": 12274,
        "geometry": { "lng": 140.87866000000002, "lat": 38.288685 }
      }
    ],
    "rentPrice": 42300
  },
  {
    "area": 185,
    "price": 34800000,
    "width": 4,
    "title": "宮城県仙台市若林区中倉３丁目",
    "agent": "reins",
    "image": "",
    "prefecture": "sendai",
    "url": "https://system.reins.jp/login/main/KG/GKG001200",
    "info": { "floorAreaRatio": 160, "buildingCoverageRatio": 60 },
    "access": "仙台東西線　卸町 徒歩　9分",
    "nearStation": [
      {
        "name": "卸町",
        "min": 9,
        "passenger": 9450,
        "geometry": { "lng": 140.92090817500002, "lat": 38.25155203 }
      }
    ],
    "rentPrice": 54300
  },
  {
    "area": 189.98,
    "price": 49800000,
    "width": 7.8,
    "title": "兵庫県神戸市長田区蓮宮通６丁目",
    "agent": "reins",
    "image": "",
    "prefecture": "hyogoMetro",
    "url": "https://system.reins.jp/login/main/KG/GKG001200",
    "info": { "floorAreaRatio": 200, "buildingCoverageRatio": 60 },
    "access": "山陽電鉄本線　西代 徒歩　5分",
    "nearStation": [
      {
        "name": "西代",
        "min": 5,
        "passenger": 6175,
        "geometry": { "lng": 135.14399, "lat": 34.662400000000005 }
      }
    ],
    "rentPrice": 53600
  },
  {
    "area": 285.61,
    "price": 34500000,
    "width": 4.5,
    "title": "北海道札幌市中央区南十八条西９丁目",
    "agent": "reins",
    "image": "",
    "prefecture": "sapporo",
    "url": "https://system.reins.jp/login/main/KG/GKG001200",
    "info": { "floorAreaRatio": 180, "buildingCoverageRatio": 60 },
    "access": "札幌市電　山鼻１９条 徒歩　7分",
    "nearStation": [
      {
        "name": "山鼻１９条",
        "min": 7,
        "passenger": 0,
        "geometry": { "lng": 0, "lat": 0 }
      }
    ],
    "rentPrice": 45000
  },
  {
    "area": 119.91,
    "price": 25000000,
    "width": 4.5,
    "title": "北海道札幌市西区琴似四条３丁目",
    "agent": "reins",
    "image": "",
    "prefecture": "sapporo",
    "url": "https://system.reins.jp/login/main/KG/GKG001200",
    "info": { "floorAreaRatio": 180, "buildingCoverageRatio": 60 },
    "access": "地下東西線　琴似 徒歩　8分",
    "nearStation": [
      {
        "name": "琴似",
        "min": 8,
        "passenger": 51634,
        "geometry": { "lng": 141.308115, "lat": 43.081095000000005 }
      }
    ],
    "rentPrice": 36000
  },
  {
    "area": 119.2,
    "price": 82000000,
    "width": 15,
    "title": "東京都荒川区荒川１丁目",
    "agent": "reins",
    "image": "",
    "prefecture": "tokyoMetro",
    "url": "https://system.reins.jp/login/main/KG/GKG001200",
    "info": { "floorAreaRatio": 400, "buildingCoverageRatio": 90 },
    "access": "都電荒川線　荒川区役所前 徒歩　2分",
    "nearStation": [
      {
        "name": "荒川区役所前",
        "min": 2,
        "passenger": 1689,
        "geometry": { "lng": 139.78601, "lat": 35.735365 }
      }
    ],
    "rentPrice": 77984
  },
  {
    "area": 130.93,
    "price": 71800000,
    "width": 5.4,
    "title": "東京都大田区羽田６丁目",
    "agent": "reins",
    "image": "",
    "prefecture": "tokyoMetro",
    "url": "https://system.reins.jp/login/main/KG/GKG001200",
    "info": { "floorAreaRatio": 200, "buildingCoverageRatio": 60 },
    "access": "京急空港線　天空橋 徒歩　6分",
    "nearStation": [
      {
        "name": "天空橋",
        "min": 6,
        "passenger": 33849,
        "geometry": { "lng": 139.75459999999998, "lat": 35.548355 }
      }
    ],
    "rentPrice": 78410
  },
  {
    "area": 186.81,
    "price": 149800000,
    "width": 4,
    "title": "東京都板橋区赤塚１丁目",
    "agent": "reins",
    "image": "",
    "prefecture": "tokyoMetro",
    "url": "https://system.reins.jp/login/main/KG/GKG001200",
    "info": { "floorAreaRatio": 160, "buildingCoverageRatio": 60 },
    "access": "東武東上線　下赤塚 徒歩　9分",
    "nearStation": [
      {
        "name": "下赤塚",
        "min": 9,
        "passenger": 16287,
        "geometry": { "lng": 139.64485000000002, "lat": 35.770485 }
      }
    ],
    "rentPrice": 76912
  },
  {
    "area": 147.85,
    "price": 27800000,
    "width": 5,
    "title": "神奈川県横須賀市田戸台",
    "agent": "reins",
    "image": "",
    "prefecture": "kanagawa",
    "url": "https://system.reins.jp/login/main/KG/GKG001200",
    "info": { "floorAreaRatio": 200, "buildingCoverageRatio": 60 },
    "access": "京浜急行線　県立大学 徒歩　7分",
    "nearStation": [
      {
        "name": "県立大学",
        "min": 7,
        "passenger": 12350,
        "geometry": { "lng": 139.676395, "lat": 35.27021 }
      }
    ],
    "rentPrice": 61990
  },
  {
    "area": 140.53,
    "price": 28800000,
    "width": 5,
    "title": "神奈川県横須賀市田戸台",
    "agent": "reins",
    "image": "",
    "prefecture": "kanagawa",
    "url": "https://system.reins.jp/login/main/KG/GKG001200",
    "info": { "floorAreaRatio": 200, "buildingCoverageRatio": 60 },
    "access": "京浜急行線　県立大学 徒歩　7分",
    "nearStation": [
      {
        "name": "県立大学",
        "min": 7,
        "passenger": 12350,
        "geometry": { "lng": 139.676395, "lat": 35.27021 }
      }
    ],
    "rentPrice": 61990
  },
  {
    "area": 275.29,
    "price": 48800000,
    "width": 4.5,
    "title": "千葉県柏市つくしが丘１丁目",
    "agent": "reins",
    "image": "",
    "prefecture": "chiba",
    "url": "https://system.reins.jp/login/main/KG/GKG001200",
    "info": { "floorAreaRatio": 100, "buildingCoverageRatio": 60 },
    "access": "東武野田線　新柏 徒歩　6分",
    "nearStation": [
      {
        "name": "新柏",
        "min": 6,
        "passenger": 20417,
        "geometry": { "lng": 139.96704, "lat": 35.8381 }
      }
    ],
    "rentPrice": 57672
  },
  {
    "area": 247.93,
    "price": 58780000,
    "width": 6,
    "title": "千葉県松戸市五香６丁目",
    "agent": "reins",
    "image": "",
    "prefecture": "chiba",
    "url": "https://system.reins.jp/login/main/KG/GKG001200",
    "info": { "floorAreaRatio": 100, "buildingCoverageRatio": 60 },
    "access": "新京成線　五香 徒歩　8分",
    "nearStation": [
      {
        "name": "五香",
        "min": 8,
        "passenger": 29725,
        "geometry": { "lng": 139.96577000000002, "lat": 35.797285 }
      }
    ],
    "rentPrice": 56638
  },
  {
    "agent": "athome",
    "url": "https://www.athome.co.jp/tochi/1015003465/?DOWN=1&BKLISTID=001LPC&sref=list_simple",
    "title": "福岡市西区 今宿１丁目 （今宿駅 ） 住宅用地",
    "image": "https://www.athome.co.jp/image_files/path/xyqTa1JzEbn224IG2XQVdQ==.jpeg?width=320&height=320&margin=true",
    "price": 45000000,
    "nearStation": [
      {
        "name": "今宿",
        "min": 4,
        "passenger": 10872,
        "geometry": { "lng": 130.274175, "lat": 33.579275 }
      }
    ],
    "access": "ＪＲ筑肥線 「今宿」駅 徒歩4分",
    "area": 126.4038,
    "prefecture": "fukuoka",
    "info": { "buildingCoverageRatio": 80, "floorAreaRatio": 200 },
    "rentPrice": 45000
  },
  {
    "agent": "athome",
    "url": "https://www.athome.co.jp/tochi/1015119522/?DOWN=1&BKLISTID=001LPC&sref=list_simple",
    "title": "名古屋市中村区 烏森町７丁目 （岩塚駅 ） 住宅用地",
    "image": "https://www.athome.co.jp/image_files/path/_gNBnQE7sJZnK76Bv8j26Q==.jpeg?width=320&height=320&margin=true",
    "price": 36000000,
    "nearStation": [
      {
        "name": "岩塚",
        "min": 10,
        "passenger": 17722,
        "geometry": { "lng": 136.854395, "lat": 35.157740000000004 }
      }
    ],
    "access": "名古屋市東山線 「岩塚」駅 徒歩10分",
    "area": 198.416,
    "prefecture": "nagoya",
    "info": { "buildingCoverageRatio": 60, "floorAreaRatio": 200 },
    "rentPrice": 51100
  },
  {
    "agent": "athome",
    "url": "https://www.athome.co.jp/tochi/1015001965/?DOWN=1&BKLISTID=001LPC&sref=list_simple",
    "title": "名古屋市瑞穂区 甲山町２丁目 （瑞穂運動場西駅 ） 住宅用地",
    "image": "https://www.athome.co.jp/image_files/path/Ba7TZ89YMtJFkEcintldrg==.jpeg?width=320&height=320&margin=true",
    "price": 77900000,
    "nearStation": [
      {
        "name": "瑞穂運動場西",
        "min": 4,
        "passenger": 7402,
        "geometry": { "lng": 136.93543499999998, "lat": 35.125095 }
      }
    ],
    "access": "名古屋市桜通線 「瑞穂運動場西」駅 徒歩4分",
    "area": 198.3359,
    "prefecture": "nagoya",
    "info": { "buildingCoverageRatio": 70, "floorAreaRatio": 200 },
    "rentPrice": 51100
  },
  {
    "agent": "athome",
    "url": "https://www.athome.co.jp/tochi/1015002665/?DOWN=1&BKLISTID=001LPC&sref=list_simple",
    "title": "札幌市東区 北二十四条東１２丁目 （元町駅 ） 住宅用地",
    "image": "https://www.athome.co.jp/image_files/path/qmofEC0uSxvBKJowSy_RWQ==.jpeg?width=320&height=320&margin=true",
    "price": 55000000,
    "nearStation": [
      {
        "name": "元町",
        "min": 5,
        "passenger": 18724,
        "geometry": { "lng": 141.371785, "lat": 43.09404 }
      }
    ],
    "access": "札幌市東豊線 「元町」駅 徒歩5分",
    "area": 220.0066,
    "prefecture": "sapporo",
    "info": { "buildingCoverageRatio": 90, "floorAreaRatio": 300 },
    "rentPrice": 31700
  },
  {
    "agent": "athome",
    "url": "https://www.athome.co.jp/tochi/1014999965/?DOWN=1&BKLISTID=001LPC&sref=list_simple",
    "title": "大阪市城東区 蒲生３丁目 （蒲生四丁目駅 ） 住宅用地",
    "image": "https://www.athome.co.jp/image_files/path/9HdIa2X1VVB-iBOyyOqXAQ==.jpeg?width=320&height=320&margin=true",
    "price": 36800000,
    "nearStation": [
      {
        "name": "蒲生四丁目",
        "min": 6,
        "passenger": 17618,
        "geometry": { "lng": 135.546295, "lat": 34.70106 }
      }
    ],
    "access": "地下鉄長堀鶴見緑地線 「蒲生四丁目」駅 徒歩6分",
    "area": 97.7529,
    "prefecture": "osakaMetro",
    "info": { "buildingCoverageRatio": 80, "floorAreaRatio": 240 },
    "rentPrice": 58100
  },
  {
    "agent": "athome",
    "url": "https://www.athome.co.jp/tochi/6977854285/?DOWN=1&BKLISTID=001LPC&sref=list_simple",
    "title": "吹田市 内本町３丁目 （吹田駅 ） 住宅用地",
    "image": "https://www.athome.co.jp/image_files/path/c4qnjgmop6Vb46aLGcUugQ==.jpeg?width=320&height=320&margin=true",
    "price": 41800000,
    "nearStation": [
      {
        "name": "吹田",
        "min": 10,
        "passenger": 60814,
        "geometry": { "lng": 135.523765, "lat": 34.763220000000004 }
      }
    ],
    "access": "阪急千里線 「吹田」駅 徒歩10分",
    "area": 133.124,
    "prefecture": "osaka",
    "info": { "buildingCoverageRatio": 60, "floorAreaRatio": 200 },
    "rentPrice": 56300
  },
  {
    "agent": "athome",
    "url": "https://www.athome.co.jp/tochi/6978928253/?DOWN=1&BKLISTID=001LPC&sref=list_simple",
    "title": "神戸市灘区 城の下通２丁目 （王子公園駅 ） 住宅用地",
    "image": "https://www.athome.co.jp/image_files/path/bcuoOmAhlzsyFiS9jhAY4g==.jpeg?width=320&height=320&margin=true",
    "price": 30000000,
    "nearStation": [
      {
        "name": "王子公園",
        "min": 13,
        "passenger": 17996,
        "geometry": { "lng": 135.21864, "lat": 34.71034 }
      }
    ],
    "access": "阪急神戸線 「王子公園」駅 徒歩13分",
    "area": 260.6678,
    "prefecture": "hyogoMetro",
    "info": { "buildingCoverageRatio": 60, "floorAreaRatio": 150 },
    "rentPrice": 51700
  },
  {
    "agent": "athome",
    "url": "https://www.athome.co.jp/tochi/1004618938/?DOWN=1&BKLISTID=001LPC&sref=list_simple",
    "title": "神戸市垂水区 歌敷山１丁目 （舞子駅 ） 住宅用地",
    "image": "https://www.athome.co.jp/image_files/path/HFLZnMhZeXipfYhgp9asRA==.jpeg?width=320&height=320&margin=true",
    "price": 39800000,
    "nearStation": [
      {
        "name": "舞子",
        "min": 9,
        "passenger": 37712,
        "geometry": { "lng": 135.034235, "lat": 34.633245 }
      }
    ],
    "access": "ＪＲ山陽本線 「舞子」駅 徒歩9分",
    "area": 149.0145,
    "prefecture": "hyogoMetro",
    "info": { "buildingCoverageRatio": 60, "floorAreaRatio": 150 },
    "rentPrice": 55000
  },
  {
    "agent": "athome",
    "url": "https://www.athome.co.jp/tochi/1004658038/?DOWN=1&BKLISTID=001LPC&sref=list_simple",
    "title": "江東区 北砂６丁目 （大島駅 ） 住宅用地",
    "image": "https://www.athome.co.jp/image_files/path/DiY5EUfE_jliPltlb3uBYg==.jpeg?width=320&height=320&margin=true",
    "price": 84800000,
    "nearStation": [
      {
        "name": "大島",
        "min": 14,
        "passenger": 34111,
        "geometry": { "lng": 139.835185, "lat": 35.689845 }
      }
    ],
    "access": "都営新宿線 「大島」駅 徒歩14分",
    "area": 158.9548,
    "prefecture": "tokyoMetro",
    "info": { "buildingCoverageRatio": 60, "floorAreaRatio": 300 },
    "rentPrice": 81852
  },
  {
    "agent": "athome",
    "url": "https://www.athome.co.jp/tochi/1014996165/?DOWN=1&BKLISTID=001LPC&sref=list_simple",
    "title": "墨田区 向島４丁目 （曳舟駅 ） 住宅用地",
    "image": "https://www.athome.co.jp/image_files/path/HDv10hEkLil51GRPoY6Zng==.jpeg?width=320&height=320&margin=true",
    "price": 90000000,
    "nearStation": [
      {
        "name": "曳舟",
        "min": 8,
        "passenger": 29498,
        "geometry": { "lng": 139.816625, "lat": 35.718085 }
      }
    ],
    "access": "東武伊勢崎線 「曳舟」駅 徒歩8分",
    "area": 113.6334,
    "prefecture": "tokyoMetro",
    "info": { "buildingCoverageRatio": 80, "floorAreaRatio": 240 },
    "rentPrice": 78869
  },
  {
    "agent": "athome",
    "url": "https://www.athome.co.jp/tochi/1071176846/?DOWN=1&BKLISTID=001LPC&sref=list_simple",
    "title": "新宿区 北新宿１丁目 （西新宿駅 ） 住宅用地",
    "image": "https://www.athome.co.jp/image_files/path/8MXZrzbApApJP1hZfXihtA==.jpeg?width=320&height=320&margin=true",
    "price": 110000000,
    "nearStation": [
      {
        "name": "西新宿",
        "min": 8,
        "passenger": 91457,
        "geometry": { "lng": 139.69256000000001, "lat": 35.694514999999996 }
      }
    ],
    "access": "東京メトロ丸ノ内線 「西新宿」駅 徒歩8分",
    "area": 117.8435,
    "prefecture": "tokyoMetro",
    "info": { "buildingCoverageRatio": 60, "floorAreaRatio": 300 },
    "rentPrice": 99239
  },
  {
    "agent": "athome",
    "url": "https://www.athome.co.jp/tochi/1085655974/?DOWN=1&BKLISTID=001LPC&sref=list_simple",
    "title": "練馬区 中村北１丁目 （練馬駅 ） 住宅用地",
    "image": "https://www.athome.co.jp/image_files/path/ZbgQ0sIX_e-zgIeCnpeaBg==.jpeg?width=320&height=320&margin=true",
    "price": 133000000,
    "nearStation": [
      {
        "name": "練馬",
        "min": 10,
        "passenger": 216276,
        "geometry": { "lng": 139.65456999999998, "lat": 35.737314999999995 }
      }
    ],
    "access": "西武池袋線 「練馬」駅 徒歩10分",
    "area": 150.2545,
    "prefecture": "tokyoMetro",
    "info": { "buildingCoverageRatio": 60, "floorAreaRatio": 200 },
    "rentPrice": 79785
  },
  {
    "agent": "athome",
    "url": "https://www.athome.co.jp/tochi/1071169546/?DOWN=1&BKLISTID=001LPC&sref=list_simple",
    "title": "大田区 西六郷２丁目 （雑色駅 ） 住宅用地",
    "image": "https://www.athome.co.jp/image_files/path/3xB82ZoCAuhRJRTaU2DAzg==.jpeg?width=320&height=320&margin=true",
    "price": 148000000,
    "nearStation": [
      {
        "name": "雑色",
        "min": 10,
        "passenger": 32138,
        "geometry": { "lng": 139.715035, "lat": 35.549775 }
      }
    ],
    "access": "京急本線 「雑色」駅 徒歩10分",
    "area": 185.9356,
    "prefecture": "tokyoMetro",
    "info": { "buildingCoverageRatio": 60, "floorAreaRatio": 200 },
    "rentPrice": 78767
  },
  {
    "agent": "athome",
    "url": "https://www.athome.co.jp/tochi/1071172146/?DOWN=1&BKLISTID=001LPC&sref=list_simple",
    "title": "横浜市港北区 大倉山３丁目 （大倉山駅 ） 住宅用地",
    "image": "https://www.athome.co.jp/image_files/path/1-yeDjg8L3bLv-8Vk-i-Mw==.jpeg?width=320&height=320&margin=true",
    "price": 128000000,
    "nearStation": [
      {
        "name": "大倉山",
        "min": 6,
        "passenger": 55464,
        "geometry": { "lng": 139.62982499999998, "lat": 35.522895000000005 }
      }
    ],
    "access": "東急東横線 「大倉山」駅 徒歩6分",
    "area": 153.1046,
    "prefecture": "kanagawaMetro",
    "info": { "buildingCoverageRatio": 60, "floorAreaRatio": 150 },
    "rentPrice": 78788
  },
  {
    "agent": "athome",
    "url": "https://www.athome.co.jp/tochi/6974867236/?DOWN=1&BKLISTID=001LPC&sref=list_simple",
    "title": "坂戸市 三光町 （坂戸駅 ） 住宅用地",
    "image": "https://www.athome.co.jp/image_files/path/xGTgo73RKZJcKiwZmYqMZg==.jpeg?width=320&height=320&margin=true",
    "price": 34800000,
    "nearStation": [
      {
        "name": "坂戸",
        "min": 10,
        "passenger": 29107,
        "geometry": { "lng": 139.394315, "lat": 35.957255 }
      }
    ],
    "access": "東武東上線 「坂戸」駅 徒歩10分",
    "area": 190.6457,
    "prefecture": "saitama",
    "info": { "buildingCoverageRatio": 60, "floorAreaRatio": 200 },
    "rentPrice": 55669
  },
  {
    "agent": "athome",
    "url": "https://www.athome.co.jp/tochi/1004657538/?DOWN=1&BKLISTID=001LPC&sref=list_simple",
    "title": "さいたま市浦和区 北浦和３丁目 （北浦和駅 ） 住宅用地",
    "image": "https://www.athome.co.jp/image_files/path/b7HO9ucrbJkVdVCdqwkqPg==.jpeg?width=320&height=320&margin=true",
    "price": 39800000,
    "nearStation": [
      {
        "name": "北浦和",
        "min": 9,
        "passenger": 106264,
        "geometry": { "lng": 139.64575000000002, "lat": 35.8722 }
      }
    ],
    "access": "ＪＲ京浜東北線 「北浦和」駅 徒歩9分",
    "area": 183.7055,
    "prefecture": "saitama",
    "info": { "buildingCoverageRatio": 60, "floorAreaRatio": 160 },
    "rentPrice": 67916
  },
  {
    "agent": "athome",
    "url": "https://www.athome.co.jp/tochi/1064629072/?DOWN=1&BKLISTID=001LPC&sref=list_simple",
    "title": "さいたま市大宮区 寿能町２丁目 （大宮公園駅 ） 住宅用地",
    "image": "https://www.athome.co.jp/image_files/path/wqD4X9J8w_wya6QbkgZG3w==.jpeg?width=320&height=320&margin=true",
    "price": 40800000,
    "nearStation": [
      {
        "name": "大宮公園",
        "min": 8,
        "passenger": 9772,
        "geometry": { "lng": 139.63308, "lat": 35.92388 }
      }
    ],
    "access": "東武野田線 「大宮公園」駅 徒歩8分",
    "area": 170.4551,
    "prefecture": "saitama",
    "info": { "buildingCoverageRatio": 40, "floorAreaRatio": 200 },
    "rentPrice": 61279
  },
  {
    "agent": "athome",
    "url": "https://www.athome.co.jp/tochi/1071171546/?DOWN=1&BKLISTID=001LPC&sref=list_simple",
    "title": "白岡市 白岡 （白岡駅 ） 住宅用地",
    "image": "https://www.athome.co.jp/image_files/path/Mds2W5mM-gzFgRTjHH2pIg==.jpeg?width=320&height=320&margin=true",
    "price": 48800000,
    "nearStation": [
      {
        "name": "白岡",
        "min": 8,
        "passenger": 25938,
        "geometry": { "lng": 139.66688, "lat": 36.01778 }
      }
    ],
    "access": "ＪＲ東北本線 「白岡」駅 徒歩8分",
    "area": 352.99106,
    "prefecture": "saitama",
    "info": { "buildingCoverageRatio": 60, "floorAreaRatio": 200 },
    "rentPrice": 59400
  },
  {
    "agent": "athome",
    "url": "https://www.athome.co.jp/tochi/1094728978/?DOWN=1&BKLISTID=001LPC&sref=list_simple",
    "title": "越谷市 北越谷４丁目 （北越谷駅 ） 住宅用地",
    "image": "https://www.athome.co.jp/image_files/path/l4mvN3vbCFxb_4JSsBuVfA==.jpeg?width=320&height=320&margin=true",
    "price": 98000000,
    "nearStation": [
      {
        "name": "北越谷",
        "min": 1,
        "passenger": 53007,
        "geometry": { "lng": 139.77987000000002, "lat": 35.901714999999996 }
      }
    ],
    "access": "東武伊勢崎線 「北越谷」駅 徒歩1分",
    "area": 150.2145,
    "prefecture": "saitama",
    "info": { "buildingCoverageRatio": 80, "floorAreaRatio": 400 },
    "rentPrice": 60872
  },
  {
    "agent": "athome",
    "url": "https://www.athome.co.jp/tochi/1040357370/?DOWN=1&BKLISTID=001LPC&sref=list_simple",
    "title": "青梅市 東青梅２丁目 （東青梅駅 ） 住宅用地",
    "image": "https://www.athome.co.jp/image_files/path/nkqBMrcF4et-6I_6btPpEA==.jpeg?width=320&height=320&margin=true",
    "price": 16800000,
    "nearStation": [
      {
        "name": "東青梅",
        "min": 4,
        "passenger": 13114,
        "geometry": { "lng": 139.272805, "lat": 35.789815000000004 }
      }
    ],
    "access": "ＪＲ青梅線 「東青梅」駅 徒歩4分",
    "area": 157.1247,
    "prefecture": "tokyo",
    "info": { "buildingCoverageRatio": 60, "floorAreaRatio": 200 },
    "rentPrice": 57373
  },
  {
    "title": "松原市上田1丁目 (河内松原駅)",
    "agent": "homes",
    "area": 129.39,
    "price": 27800000,
    "info": { "buildingCoverageRatio": 60, "floorAreaRatio": 200 },
    "prefecture": "osaka",
    "image": "https://image.homes.jp/smallimg/image.php?file=http%3A%2F%2Fimg.homes.jp%2Fot6h2qjuogdzyg1.jpg&width=208&height=138",
    "nearStation": [
      {
        "name": "河内松原",
        "min": 5,
        "passenger": 29976,
        "geometry": { "lng": 135.557415, "lat": 34.575495000000004 }
      }
    ],
    "url": "https://www.homes.co.jp/tochi/b-88810004168/",
    "access": "近鉄南大阪線 河内松原駅 徒歩5分",
    "rentPrice": 52600
  },
  {
    "title": "西宮市産所町 (さくら夙川駅)",
    "agent": "homes",
    "area": 157.85,
    "price": 85000000,
    "info": { "buildingCoverageRatio": 60, "floorAreaRatio": 200 },
    "prefecture": "hyogo",
    "image": "https://image1.homes.jp/smallimg/image.php?file=http%3A%2F%2Fimg.homes.jp%2Flgji2rnlvr10t9l.jpg&width=208&height=138",
    "nearStation": [
      {
        "name": "さくら夙川",
        "min": 5,
        "passenger": 16746,
        "geometry": { "lng": 135.331795, "lat": 34.73904 }
      }
    ],
    "url": "https://www.homes.co.jp/tochi/b-1210360000474/",
    "access": "JR東海道・山陽本線 さくら夙川駅 徒歩5分",
    "rentPrice": 52500
  },
  {
    "title": "明石市二見町東二見 (東二見駅)",
    "agent": "homes",
    "area": 166.56,
    "price": 21000000,
    "info": { "buildingCoverageRatio": 60, "floorAreaRatio": 160 },
    "prefecture": "hyogo",
    "image": "https://image3.homes.jp/smallimg/image.php?file=http%3A%2F%2Fimg.homes.jp%2F8azp2rqo4gb2b1h.jpg&width=208&height=138",
    "nearStation": [
      {
        "name": "東二見",
        "min": 8,
        "passenger": 7034,
        "geometry": { "lng": 134.888025, "lat": 34.70025 }
      }
    ],
    "url": "https://www.homes.co.jp/tochi/b-1296750008769/",
    "access": "山陽電鉄本線 東二見駅 徒歩8分",
    "rentPrice": 47100
  },
  {
    "title": "ふじみ野市上福岡1丁目 (上福岡駅)",
    "agent": "homes",
    "area": 165.33,
    "price": 55000000,
    "info": { "buildingCoverageRatio": 80, "floorAreaRatio": 400 },
    "prefecture": "saitama",
    "image": "https://image2.homes.jp/smallimg/image.php?file=http%3A%2F%2Fimg.homes.jp%2Ff1of2riqrhpeist.jpg&width=208&height=138",
    "nearStation": [
      {
        "name": "上福岡",
        "min": 5,
        "passenger": 56428,
        "geometry": { "lng": 139.51187, "lat": 35.87387 }
      }
    ],
    "url": "https://www.homes.co.jp/tochi/b-1073130004899/",
    "access": "東武東上線 上福岡駅 徒歩5分",
    "rentPrice": 56132
  },
  {
    "title": "さいたま市大宮区寿能町2丁目 (大宮公園駅)",
    "agent": "homes",
    "area": 201.33,
    "price": 46000000,
    "info": { "buildingCoverageRatio": 40, "floorAreaRatio": 200 },
    "prefecture": "saitama",
    "image": "https://image3.homes.jp/smallimg/image.php?file=http%3A%2F%2Fimg.homes.jp%2F1sj62rwxfi954ne.jpg&width=208&height=138",
    "nearStation": [
      {
        "name": "大宮公園",
        "min": 8,
        "passenger": 9772,
        "geometry": { "lng": 139.63308, "lat": 35.92388 }
      }
    ],
    "url": "https://www.homes.co.jp/tochi/b-1473310001090/",
    "access": "東武野田線 大宮公園駅 徒歩8分",
    "rentPrice": 61279
  },
  {
    "title": "さいたま市大宮区寿能町2丁目 (大宮公園駅)",
    "agent": "homes",
    "area": 165.99,
    "price": 39800000,
    "info": { "buildingCoverageRatio": 40, "floorAreaRatio": 200 },
    "prefecture": "saitama",
    "image": "https://image4.homes.jp/smallimg/image.php?file=http%3A%2F%2Fimg.homes.jp%2F2mjd2rwxfi954hu.jpg&width=208&height=138",
    "nearStation": [
      {
        "name": "大宮公園",
        "min": 8,
        "passenger": 9772,
        "geometry": { "lng": 139.63308, "lat": 35.92388 }
      }
    ],
    "url": "https://www.homes.co.jp/tochi/b-1473310001088/",
    "access": "東武野田線 大宮公園駅 徒歩8分",
    "rentPrice": 61279
  },
  {
    "area": 258.87,
    "price": 29900000,
    "width": 6.2,
    "title": "愛知県名古屋市港区錦町",
    "agent": "reins",
    "image": "",
    "prefecture": "nagoya",
    "url": "https://system.reins.jp/login/main/KG/GKG001200",
    "info": { "floorAreaRatio": 200, "buildingCoverageRatio": 70 },
    "access": "あおなみ線　稲永 徒歩　8分",
    "nearStation": [
      {
        "name": "稲永",
        "min": 8,
        "passenger": 5400,
        "geometry": { "lng": 136.86336, "lat": 35.09151 }
      }
    ],
    "rentPrice": 48300
  },
  {
    "area": 198.33,
    "price": 77900000,
    "width": 9.1,
    "title": "愛知県名古屋市瑞穂区甲山町２丁目",
    "agent": "reins",
    "image": "",
    "prefecture": "nagoya",
    "url": "https://system.reins.jp/login/main/KG/GKG001200",
    "info": { "floorAreaRatio": 200, "buildingCoverageRatio": 80 },
    "access": "桜通線　瑞穂運動場西 徒歩　4分",
    "nearStation": [
      {
        "name": "瑞穂運動場西",
        "min": 4,
        "passenger": 7402,
        "geometry": { "lng": 136.93543499999998, "lat": 35.125095 }
      }
    ],
    "rentPrice": 51100
  },
  {
    "area": 135.58,
    "price": 108000000,
    "width": 7.9,
    "title": "兵庫県神戸市東灘区御影中町６丁目",
    "agent": "reins",
    "image": "",
    "prefecture": "hyogoMetro",
    "url": "https://system.reins.jp/login/main/KG/GKG001200",
    "info": { "floorAreaRatio": 300, "buildingCoverageRatio": 60 },
    "access": "阪神本線　御影 徒歩　9分",
    "nearStation": [
      {
        "name": "御影",
        "min": 9,
        "passenger": 44061,
        "geometry": { "lng": 135.25598, "lat": 34.714925 }
      }
    ],
    "rentPrice": 50100
  },
  {
    "area": 232.67,
    "price": 51800000,
    "width": 8,
    "title": "北海道札幌市西区二十四軒一条６丁目",
    "agent": "reins",
    "image": "",
    "prefecture": "sapporo",
    "url": "https://system.reins.jp/login/main/KG/GKG001200",
    "info": { "floorAreaRatio": 200, "buildingCoverageRatio": 60 },
    "access": "地下東西線　二十四軒 徒歩　3分",
    "nearStation": [
      {
        "name": "二十四軒",
        "min": 3,
        "passenger": 13028,
        "geometry": { "lng": 141.313605, "lat": 43.07045 }
      }
    ],
    "rentPrice": 35600
  },
  {
    "area": 262.81,
    "price": 60000000,
    "width": 20,
    "title": "北海道札幌市中央区南二十一条西８丁目",
    "agent": "reins",
    "image": "",
    "prefecture": "sapporo",
    "url": "https://system.reins.jp/login/main/KG/GKG001200",
    "info": { "floorAreaRatio": 300, "buildingCoverageRatio": 80 },
    "access": "札幌市電　東屯田通 徒歩　2分",
    "nearStation": [
      {
        "name": "東屯田通",
        "min": 2,
        "passenger": 1982,
        "geometry": { "lng": 141.348835, "lat": 43.031045 }
      }
    ],
    "rentPrice": 31400
  },
  {
    "area": 125.5,
    "price": 16800000,
    "width": 4.4,
    "title": "北海道札幌市西区八軒三条東４丁目",
    "agent": "reins",
    "image": "",
    "prefecture": "sapporo",
    "url": "https://system.reins.jp/login/main/KG/GKG001200",
    "info": { "floorAreaRatio": 176, "buildingCoverageRatio": 60 },
    "access": "札沼線　八軒 徒歩　10分",
    "nearStation": [
      {
        "name": "八軒",
        "min": 10,
        "passenger": 5008,
        "geometry": { "lng": 141.31915500000002, "lat": 43.086315 }
      }
    ],
    "rentPrice": 37800
  },
  {
    "area": 259.62,
    "price": 49800000,
    "width": 6,
    "title": "北海道札幌市白石区本通１７丁目南",
    "agent": "reins",
    "image": "",
    "prefecture": "sapporo",
    "url": "https://system.reins.jp/login/main/KG/GKG001200",
    "info": { "floorAreaRatio": 200, "buildingCoverageRatio": 70 },
    "access": "地下東西線　南郷１８丁目 徒歩　7分",
    "nearStation": [
      {
        "name": "南郷１８丁目",
        "min": 7,
        "passenger": 0,
        "geometry": { "lng": 0, "lat": 0 }
      }
    ],
    "rentPrice": 45000
  },
  {
    "area": 254,
    "price": 59800000,
    "width": 5.4,
    "title": "北海道札幌市中央区北十三条西１５丁目",
    "agent": "reins",
    "image": "",
    "prefecture": "sapporo",
    "url": "https://system.reins.jp/login/main/KG/GKG001200",
    "info": { "floorAreaRatio": 200, "buildingCoverageRatio": 60 },
    "access": "函館線　桑園 徒歩　7分",
    "nearStation": [
      {
        "name": "桑園",
        "min": 7,
        "passenger": 21154,
        "geometry": { "lng": 141.33266, "lat": 43.07042 }
      }
    ],
    "rentPrice": 40000
  },
  {
    "area": 264.46,
    "price": 78000000,
    "width": 8,
    "title": "北海道札幌市豊平区美園八条３丁目",
    "agent": "reins",
    "image": "",
    "prefecture": "sapporo",
    "url": "https://system.reins.jp/login/main/KG/GKG001200",
    "info": { "floorAreaRatio": 300, "buildingCoverageRatio": 80 },
    "access": "地下東豊線　豊平公園 徒歩　5分",
    "nearStation": [
      {
        "name": "豊平公園",
        "min": 5,
        "passenger": 11140,
        "geometry": { "lng": 141.37616500000001, "lat": 43.042109999999994 }
      }
    ],
    "rentPrice": 35900
  },
  {
    "area": 99.57,
    "price": 61800000,
    "width": 4.1,
    "title": "東京都荒川区東尾久２丁目",
    "agent": "reins",
    "image": "",
    "prefecture": "tokyoMetro",
    "url": "https://system.reins.jp/login/main/KG/GKG001200",
    "info": {
      "floorAreaRatio": 245.99999999999997,
      "buildingCoverageRatio": 100
    },
    "access": "日暮里舎人　赤土小学校前 徒歩　3分",
    "nearStation": [
      {
        "name": "赤土小学校前",
        "min": 3,
        "passenger": 5216,
        "geometry": { "lng": 139.76913000000002, "lat": 35.74306 }
      }
    ],
    "rentPrice": 78638
  },
  {
    "area": 89,
    "price": 48500000,
    "width": 5,
    "title": "東京都足立区六町３丁目",
    "agent": "reins",
    "image": "",
    "prefecture": "tokyoMetro",
    "url": "https://system.reins.jp/login/main/KG/GKG001200",
    "info": { "floorAreaRatio": 200, "buildingCoverageRatio": 80 },
    "access": "つくばＥＸ　六町 徒歩　7分",
    "nearStation": [
      {
        "name": "六町",
        "min": 7,
        "passenger": 30100,
        "geometry": { "lng": 139.82180499999998, "lat": 35.78478 }
      }
    ],
    "rentPrice": 67700
  },
  {
    "area": 218.81,
    "price": 138000000,
    "width": 11,
    "title": "東京都練馬区下石神井５丁目",
    "agent": "reins",
    "image": "",
    "prefecture": "tokyoMetro",
    "url": "https://system.reins.jp/login/main/KG/GKG001200",
    "info": { "floorAreaRatio": 300, "buildingCoverageRatio": 60 },
    "access": "西武新宿線　上井草 徒歩　12分",
    "nearStation": [
      {
        "name": "上井草",
        "min": 12,
        "passenger": 21302,
        "geometry": { "lng": 139.602955, "lat": 35.725255 }
      }
    ],
    "rentPrice": 75759
  },
  {
    "area": 124,
    "price": 40800000,
    "width": 11,
    "title": "千葉県市川市香取２丁目",
    "agent": "reins",
    "image": "",
    "prefecture": "chiba",
    "url": "https://system.reins.jp/login/main/KG/GKG001200",
    "info": { "floorAreaRatio": 200, "buildingCoverageRatio": 60 },
    "access": "東西線　行徳 徒歩　10分",
    "nearStation": [
      {
        "name": "行徳",
        "min": 10,
        "passenger": 57818,
        "geometry": { "lng": 139.91395, "lat": 35.682424999999995 }
      }
    ],
    "rentPrice": 73061
  },
  {
    "area": 202.53,
    "price": 29800000,
    "width": 6,
    "title": "千葉県柏市増尾１丁目",
    "agent": "reins",
    "image": "",
    "prefecture": "chiba",
    "url": "https://system.reins.jp/login/main/KG/GKG001200",
    "info": { "floorAreaRatio": 150, "buildingCoverageRatio": 70 },
    "access": "東武野田線　増尾 徒歩　6分",
    "nearStation": [
      {
        "name": "増尾",
        "min": 6,
        "passenger": 13089,
        "geometry": { "lng": 139.97632499999997, "lat": 35.82982 }
      }
    ],
    "rentPrice": 53262
  },
  {
    "area": 179.96,
    "price": 79800000,
    "width": 4,
    "title": "大阪府大阪市旭区森小路１丁目",
    "agent": "reins",
    "image": "",
    "prefecture": "osakaMetro",
    "url": "https://system.reins.jp/login/main/KG/GKG001200",
    "info": { "floorAreaRatio": 160, "buildingCoverageRatio": 80 },
    "access": "京阪本線　森小路 徒歩　2分",
    "nearStation": [
      {
        "name": "森小路",
        "min": 2,
        "passenger": 8238,
        "geometry": { "lng": 135.55168, "lat": 34.719454999999996 }
      }
    ],
    "rentPrice": 44300
  },
  {
    "title": "東京都葛飾区西亀有４",
    "url": "https://suumo.jp/tochi/__JJ_JJ010FJ100_arz1030z2bsz1030z2ncz172003385.html",
    "image": "https://img01.suumo.com/jj/resizeImage?src=gazo%2Fbukken%2F030%2FN010000%2Fimg%2F385%2F72003385%2F72003385_0001.jpg&w=132&h=99",
    "agent": "suumo",
    "prefecture": "tokyoMetro",
    "area": 150.99,
    "price": 69800000,
    "access": "ＪＲ常磐線「亀有」徒歩9分",
    "nearStation": [
      {
        "name": "亀有",
        "min": 9,
        "passenger": 85708,
        "geometry": { "lng": 139.84807999999998, "lat": 35.766765 }
      }
    ],
    "info": { "buildingCoverageRatio": 60, "floorAreaRatio": 160 },
    "rentPrice": 72930
  },
  {
    "title": "東京都板橋区東新町１",
    "url": "https://suumo.jp/tochi/__JJ_JJ010FJ100_arz1030z2bsz1030z2ncz172149562.html",
    "image": "https://img01.suumo.com/jj/resizeImage?src=gazo%2Fbukken%2F030%2FN010000%2Fimg%2F562%2F72149562%2F72149562_0001.jpg&w=132&h=99",
    "agent": "suumo",
    "prefecture": "tokyoMetro",
    "area": 119.36,
    "price": 74800000,
    "access": "東武東上線「上板橋」徒歩7分",
    "nearStation": [
      {
        "name": "上板橋",
        "min": 7,
        "passenger": 51929,
        "geometry": { "lng": 139.67620499999998, "lat": 35.763615 }
      }
    ],
    "info": { "buildingCoverageRatio": 60, "floorAreaRatio": 200 },
    "rentPrice": 75428
  },
  {
    "title": "東京都練馬区石神井台７",
    "url": "https://suumo.jp/tochi/__JJ_JJ010FJ100_arz1030z2bsz1030z2ncz172147862.html",
    "image": "https://img01.suumo.com/jj/resizeImage?src=gazo%2Fbukken%2F030%2FN010000%2Fimg%2F862%2F72147862%2F72147862_0001.jpg&w=132&h=99",
    "agent": "suumo",
    "prefecture": "tokyoMetro",
    "area": 123,
    "price": 62000000,
    "access": "西武新宿線「武蔵関」徒歩7分",
    "nearStation": [
      {
        "name": "武蔵関",
        "min": 7,
        "passenger": 32351,
        "geometry": { "lng": 139.576365, "lat": 35.727615 }
      }
    ],
    "info": { "buildingCoverageRatio": 60, "floorAreaRatio": 200 },
    "rentPrice": 75417
  },
  {
    "title": "東京都板橋区前野町５",
    "url": "https://suumo.jp/tochi/__JJ_JJ010FJ100_arz1030z2bsz1030z2ncz172172854.html",
    "image": "https://img01.suumo.com/jj/resizeImage?src=gazo%2Fbukken%2Fsystem%2Fimg%2FDummy_Photo_030_132_99.jpg&w=132&h=99",
    "agent": "suumo",
    "prefecture": "tokyoMetro",
    "area": 122.3,
    "price": 59000000,
    "access": "都営三田線「志村三丁目」徒歩13分",
    "nearStation": [
      {
        "name": "志村三丁目",
        "min": 13,
        "passenger": 32536,
        "geometry": { "lng": 139.68586, "lat": 35.777465 }
      }
    ],
    "info": { "buildingCoverageRatio": 60, "floorAreaRatio": 200 },
    "rentPrice": 73566
  },
  {
    "title": "東京都江東区南砂５",
    "url": "https://suumo.jp/tochi/__JJ_JJ010FJ100_arz1030z2bsz1030z2ncz172171384.html",
    "image": "https://img01.suumo.com/jj/resizeImage?src=gazo%2Fbukken%2F030%2FN010000%2Fimg%2F384%2F72171384%2F72171384_0013.jpg&w=132&h=99",
    "agent": "suumo",
    "prefecture": "tokyoMetro",
    "area": 87.07,
    "price": 52800000,
    "access": "東京メトロ東西線「南砂町」徒歩10分",
    "nearStation": [
      {
        "name": "南砂町",
        "min": 10,
        "passenger": 60969,
        "geometry": { "lng": 139.831695, "lat": 35.668414999999996 }
      }
    ],
    "info": { "buildingCoverageRatio": 60, "floorAreaRatio": 300 },
    "rentPrice": 82458
  },
  {
    "title": "神奈川県横浜市緑区西八朔町",
    "url": "https://suumo.jp/tochi/__JJ_JJ010FJ100_arz1030z2bsz1030z2ncz172089269.html",
    "image": "https://img01.suumo.com/jj/resizeImage?src=gazo%2Fbukken%2F030%2FN010000%2Fimg%2F269%2F72089269%2F72089269_0001.jpg&w=132&h=99",
    "agent": "suumo",
    "prefecture": "kanagawaMetro",
    "area": 354.64,
    "price": 84800000,
    "access": "ＪＲ横浜線「十日市場」徒歩12分",
    "nearStation": [
      {
        "name": "十日市場",
        "min": 12,
        "passenger": 41608,
        "geometry": { "lng": 139.51712500000002, "lat": 35.526070000000004 }
      }
    ],
    "info": { "buildingCoverageRatio": 60, "floorAreaRatio": 200 },
    "rentPrice": 69801
  },
  {
    "title": "神奈川県横浜市中区元町４",
    "url": "https://suumo.jp/tochi/__JJ_JJ010FJ100_arz1030z2bsz1030z2ncz172173229.html",
    "image": "https://img01.suumo.com/jj/resizeImage?src=gazo%2Fbukken%2F030%2FN010000%2Fimg%2F229%2F72173229%2F72173229_0001.jpg&w=132&h=99",
    "agent": "suumo",
    "prefecture": "kanagawaMetro",
    "area": 120.49,
    "price": 89800000,
    "access": "みなとみらい線「元町・中華街」徒歩8分",
    "nearStation": [
      {
        "name": "元町・中華街",
        "min": 8,
        "passenger": 63291,
        "geometry": { "lng": 139.65073999999998, "lat": 35.442305000000005 }
      }
    ],
    "info": { "buildingCoverageRatio": 80, "floorAreaRatio": 240 },
    "rentPrice": 50000
  },
  {
    "title": "大阪府豊中市螢池東町４",
    "url": "https://suumo.jp/tochi/__JJ_JJ010FJ100_arz1060z2bsz1030z2ncz171387481.html",
    "image": "https://img01.suumo.com/jj/resizeImage?src=gazo%2Fbukken%2F060%2FN010000%2Fimg%2F481%2F71387481%2F71387481_0007.jpg&w=132&h=99",
    "agent": "suumo",
    "prefecture": "osaka",
    "area": 281.63,
    "price": 59800000,
    "access": "阪急宝塚線「蛍池」徒歩9分",
    "nearStation": [
      {
        "name": "蛍池",
        "min": 9,
        "passenger": 70909,
        "geometry": { "lng": 135.44931, "lat": 34.793925 }
      }
    ],
    "info": { "buildingCoverageRatio": 60, "floorAreaRatio": 200 },
    "rentPrice": 48200
  },
  {
    "title": "大阪府枚方市津田駅前１",
    "url": "https://suumo.jp/tochi/__JJ_JJ010FJ100_arz1060z2bsz1030z2ncz171166273.html",
    "image": "https://img01.suumo.com/jj/resizeImage?src=gazo%2Fbukken%2F060%2FN010000%2Fimg%2F273%2F71166273%2F71166273_0001.jpg&w=132&h=99",
    "agent": "suumo",
    "prefecture": "osaka",
    "area": 113.5,
    "price": 21800000,
    "access": "ＪＲ片町線「津田」徒歩2分",
    "nearStation": [
      {
        "name": "津田",
        "min": 2,
        "passenger": 11292,
        "geometry": { "lng": 135.69797499999999, "lat": 34.80141 }
      }
    ],
    "info": { "buildingCoverageRatio": 80, "floorAreaRatio": 300 },
    "rentPrice": 46900
  },
  {
    "title": "大阪府八尾市西山本町７-8-17付近",
    "url": "https://suumo.jp/tochi/__JJ_JJ010FJ100_arz1060z2bsz1030z2ncz170806954.html",
    "image": "https://img01.suumo.com/jj/resizeImage?src=gazo%2Fbukken%2F060%2FN010000%2Fimg%2F954%2F70806954%2F70806954_0001.jpg&w=132&h=99",
    "agent": "suumo",
    "prefecture": "osaka",
    "area": 221,
    "price": 53800000,
    "access": "近鉄大阪線「河内山本」徒歩7分",
    "nearStation": [
      {
        "name": "河内山本",
        "min": 7,
        "passenger": 20281,
        "geometry": { "lng": 135.61917, "lat": 34.627925 }
      }
    ],
    "info": { "buildingCoverageRatio": 60, "floorAreaRatio": 200 },
    "rentPrice": 43500
  },
  {
    "title": "大阪府堺市堺区中田出井町３",
    "url": "https://suumo.jp/tochi/__JJ_JJ010FJ100_arz1060z2bsz1030z2ncz172144211.html",
    "image": "https://img01.suumo.com/jj/resizeImage?src=gazo%2Fbukken%2F060%2FN010000%2Fimg%2F211%2F72144211%2F72144211_0001.jpg&w=132&h=99",
    "agent": "suumo",
    "prefecture": "osaka",
    "area": 207.78,
    "price": 62850000,
    "access": "南海高野線「堺東」徒歩11分",
    "nearStation": [
      {
        "name": "堺東",
        "min": 11,
        "passenger": 60454,
        "geometry": { "lng": 135.48503, "lat": 34.575855000000004 }
      }
    ],
    "info": { "buildingCoverageRatio": 60, "floorAreaRatio": 200 },
    "rentPrice": 52000
  },
  {
    "title": "大阪府東大阪市長堂１",
    "url": "https://suumo.jp/tochi/__JJ_JJ010FJ100_arz1060z2bsz1030z2ncz172173759.html",
    "image": "https://img01.suumo.com/jj/resizeImage?src=gazo%2Fbukken%2F060%2FN010000%2Fimg%2F759%2F72173759%2F72173759_0001.jpg&w=132&h=99",
    "agent": "suumo",
    "prefecture": "osaka",
    "area": 102.18,
    "price": 55000000,
    "access": "近鉄大阪線「布施」徒歩4分",
    "nearStation": [
      {
        "name": "布施",
        "min": 4,
        "passenger": 39370,
        "geometry": { "lng": 135.56357, "lat": 34.664085 }
      }
    ],
    "info": { "buildingCoverageRatio": 80, "floorAreaRatio": 312 },
    "rentPrice": 56300
  },
  {
    "title": "大阪府枚方市藤阪元町３",
    "url": "https://suumo.jp/tochi/__JJ_JJ010FJ100_arz1060z2bsz1030z2ncz172138007.html",
    "image": "https://img01.suumo.com/jj/resizeImage?src=gazo%2Fbukken%2Fsystem%2Fimg%2FDummy_Photo_030_132_99.jpg&w=132&h=99",
    "agent": "suumo",
    "prefecture": "osaka",
    "area": 378.12,
    "price": 30000000,
    "access": "ＪＲ片町線「藤阪」徒歩11分",
    "nearStation": [
      {
        "name": "藤阪",
        "min": 11,
        "passenger": 6432,
        "geometry": { "lng": 135.70274999999998, "lat": 34.814440000000005 }
      }
    ],
    "info": { "buildingCoverageRatio": 60, "floorAreaRatio": 188 },
    "rentPrice": 39900
  },
  {
    "title": "大阪府八尾市明美町２",
    "url": "https://suumo.jp/tochi/__JJ_JJ010FJ100_arz1060z2bsz1030z2ncz172140378.html",
    "image": "https://img01.suumo.com/jj/resizeImage?src=gazo%2Fbukken%2F060%2FN010000%2Fimg%2F378%2F72140378%2F72140378_0001.jpg&w=132&h=99",
    "agent": "suumo",
    "prefecture": "osaka",
    "area": 116.32,
    "price": 24800000,
    "access": "ＪＲ関西本線「八尾」徒歩9分",
    "nearStation": [
      {
        "name": "八尾",
        "min": 9,
        "passenger": 26330,
        "geometry": { "lng": 135.59701, "lat": 34.617255 }
      }
    ],
    "info": { "buildingCoverageRatio": 60, "floorAreaRatio": 200 },
    "rentPrice": 48700
  },
  {
    "title": "大阪府八尾市東山本町１-15-18",
    "url": "https://suumo.jp/tochi/__JJ_JJ010FJ100_arz1060z2bsz1030z2ncz172143096.html",
    "image": "https://img01.suumo.com/jj/resizeImage?src=gazo%2Fbukken%2F060%2FN010000%2Fimg%2F096%2F72143096%2F72143096_0016.jpg&w=132&h=99",
    "agent": "suumo",
    "prefecture": "osaka",
    "area": 117.93,
    "price": 24800000,
    "access": "近鉄大阪線「河内山本」徒歩6分",
    "nearStation": [
      {
        "name": "河内山本",
        "min": 6,
        "passenger": 20281,
        "geometry": { "lng": 135.61917, "lat": 34.627925 }
      }
    ],
    "info": { "buildingCoverageRatio": 60, "floorAreaRatio": 200 },
    "rentPrice": 43500
  },
  {
    "title": "愛知県名古屋市千種区仲田２",
    "url": "https://suumo.jp/tochi/__JJ_JJ010FJ100_arz1050z2bsz1030z2ncz198465888.html",
    "image": "https://img01.suumo.com/jj/resizeImage?src=gazo%2Fbukken%2F050%2FN010000%2Fimg%2F888%2F98465888%2F98465888_0030.jpg&w=132&h=99",
    "agent": "suumo",
    "prefecture": "nagoya",
    "area": 142.07,
    "price": 74800000,
    "access": "地下鉄東山線「今池」徒歩6分",
    "nearStation": [
      {
        "name": "今池",
        "min": 6,
        "passenger": 47924,
        "geometry": { "lng": 136.937005, "lat": 35.168975 }
      }
    ],
    "info": { "buildingCoverageRatio": 80, "floorAreaRatio": 400 },
    "rentPrice": 59800
  },
  {
    "title": "愛知県名古屋市千種区振甫町２",
    "url": "https://suumo.jp/tochi/__JJ_JJ010FJ100_arz1050z2bsz1030z2ncz170974377.html",
    "image": "https://img01.suumo.com/jj/resizeImage?src=gazo%2Fbukken%2F050%2FN010000%2Fimg%2F377%2F70974377%2F70974377_0002.jpg&w=132&h=99",
    "agent": "suumo",
    "prefecture": "nagoya",
    "area": 173.92,
    "price": 21800000,
    "access": "地下鉄東山線「池下」徒歩12分",
    "nearStation": [
      {
        "name": "池下",
        "min": 12,
        "passenger": 27468,
        "geometry": { "lng": 136.94602500000002, "lat": 35.167825 }
      }
    ],
    "info": { "buildingCoverageRatio": 60, "floorAreaRatio": 160 },
    "rentPrice": 59500
  },
  {
    "title": "愛知県名古屋市西区稲生町４",
    "url": "https://suumo.jp/tochi/__JJ_JJ010FJ100_arz1050z2bsz1030z2ncz172146931.html",
    "image": "https://img01.suumo.com/jj/resizeImage?src=gazo%2Fbukken%2F050%2FN010000%2Fimg%2F931%2F72146931%2F72146931_0001.jpg&w=132&h=99",
    "agent": "suumo",
    "prefecture": "nagoya",
    "area": 241.32,
    "price": 55500000,
    "access": "地下鉄鶴舞線「庄内通」徒歩11分",
    "nearStation": [
      {
        "name": "庄内通",
        "min": 11,
        "passenger": 14880,
        "geometry": { "lng": 136.891005, "lat": 35.203815000000006 }
      }
    ],
    "info": { "buildingCoverageRatio": 60, "floorAreaRatio": 200 },
    "rentPrice": 51600
  },
  {
    "title": "千葉県柏市加賀３-8-7",
    "url": "https://suumo.jp/tochi/__JJ_JJ010FJ100_arz1030z2bsz1030z2ncz171847502.html",
    "image": "https://img01.suumo.com/jj/resizeImage?src=gazo%2Fbukken%2F030%2FN010000%2Fimg%2F502%2F71847502%2F71847502_0010.jpg&w=132&h=99",
    "agent": "suumo",
    "prefecture": "chiba",
    "area": 169.89,
    "price": 30800000,
    "access": "東武野田線「増尾」徒歩6分",
    "nearStation": [
      {
        "name": "増尾",
        "min": 6,
        "passenger": 13089,
        "geometry": { "lng": 139.97632499999997, "lat": 35.82982 }
      }
    ],
    "info": { "buildingCoverageRatio": 70, "floorAreaRatio": 200 },
    "rentPrice": 53262
  },
  {
    "title": "千葉県千葉市緑区あすみが丘１",
    "url": "https://suumo.jp/tochi/__JJ_JJ010FJ100_arz1030z2bsz1030z2ncz172174429.html",
    "image": "https://img01.suumo.com/jj/resizeImage?src=gazo%2Fbukken%2F030%2FN010000%2Fimg%2F429%2F72174429%2F72174429_0001.jpg&w=132&h=99",
    "agent": "suumo",
    "prefecture": "chiba",
    "area": 151,
    "price": 20500000,
    "access": "ＪＲ外房線「土気」徒歩7分",
    "nearStation": [
      {
        "name": "土気",
        "min": 7,
        "passenger": 26670,
        "geometry": { "lng": 140.270645, "lat": 35.53063 }
      }
    ],
    "info": { "buildingCoverageRatio": 60, "floorAreaRatio": 200 },
    "rentPrice": 50000
  },
  {
    "title": "大阪府大阪市港区市岡３",
    "url": "https://suumo.jp/tochi/__JJ_JJ010FJ100_arz1060z2bsz1030z2ncz171218152.html",
    "image": "https://img01.suumo.com/jj/resizeImage?src=gazo%2Fbukken%2F060%2FN010000%2Fimg%2F152%2F71218152%2F71218152_0008.jpg&w=132&h=99",
    "agent": "suumo",
    "prefecture": "osakaMetro",
    "area": 109.36,
    "price": 31700000,
    "access": "ＪＲ大阪環状線「弁天町」徒歩15分",
    "nearStation": [
      {
        "name": "弁天町",
        "min": 15,
        "passenger": 109122,
        "geometry": { "lng": 135.46244000000002, "lat": 34.66856 }
      }
    ],
    "info": { "buildingCoverageRatio": 60, "floorAreaRatio": 200 },
    "rentPrice": 56300
  },
  {
    "title": "大阪府大阪市東住吉区北田辺６-14-16",
    "url": "https://suumo.jp/tochi/__JJ_JJ010FJ100_arz1060z2bsz1030z2ncz172160336.html",
    "image": "https://img01.suumo.com/jj/resizeImage?src=gazo%2Fbukken%2Fsystem%2Fimg%2FDummy_Photo_030_132_99.jpg&w=132&h=99",
    "agent": "suumo",
    "prefecture": "osakaMetro",
    "area": 151.42,
    "price": 53900000,
    "access": "地下鉄谷町線「田辺」徒歩5分",
    "nearStation": [
      {
        "name": "田辺",
        "min": 5,
        "passenger": 9608,
        "geometry": { "lng": 135.524675, "lat": 34.629145 }
      }
    ],
    "info": { "buildingCoverageRatio": 80, "floorAreaRatio": 300 },
    "rentPrice": 49500
  },
  {
    "title": "大阪府大阪市住吉区清水丘２",
    "url": "https://suumo.jp/tochi/__JJ_JJ010FJ100_arz1060z2bsz1030z2ncz172128866.html",
    "image": "https://img01.suumo.com/jj/resizeImage?src=gazo%2Fbukken%2F060%2FN010000%2Fimg%2F866%2F72128866%2F72128866_0001.jpg&w=132&h=99",
    "agent": "suumo",
    "prefecture": "osakaMetro",
    "area": 146.38,
    "price": 48500000,
    "access": "南海高野線「我孫子前」徒歩6分",
    "nearStation": [
      {
        "name": "我孫子前",
        "min": 6,
        "passenger": 8563,
        "geometry": { "lng": 135.49690500000003, "lat": 34.60002 }
      }
    ],
    "info": { "buildingCoverageRatio": 80, "floorAreaRatio": 200 },
    "rentPrice": 42300
  },
  {
    "title": "大阪府大阪市港区築港１-13-32",
    "url": "https://suumo.jp/tochi/__JJ_JJ010FJ100_arz1060z2bsz1030z2ncz171976347.html",
    "image": "https://img01.suumo.com/jj/resizeImage?src=gazo%2Fbukken%2F060%2FN010000%2Fimg%2F347%2F71976347%2F71976347_0001.jpg&w=132&h=99",
    "agent": "suumo",
    "prefecture": "osakaMetro",
    "area": 97.86,
    "price": 33900000,
    "access": "地下鉄中央線「大阪港」徒歩2分",
    "nearStation": [
      {
        "name": "大阪港",
        "min": 2,
        "passenger": 21960,
        "geometry": { "lng": 135.433785, "lat": 34.653655 }
      }
    ],
    "info": { "buildingCoverageRatio": 80, "floorAreaRatio": 300 },
    "rentPrice": 51800
  },
  {
    "title": "大阪府大阪市西淀川区福町２",
    "url": "https://suumo.jp/tochi/__JJ_JJ010FJ100_arz1060z2bsz1030z2ncz172147265.html",
    "image": "https://img01.suumo.com/jj/resizeImage?src=gazo%2Fbukken%2F060%2FN010000%2Fimg%2F265%2F72147265%2F72147265_0001.jpg&w=132&h=99",
    "agent": "suumo",
    "prefecture": "osakaMetro",
    "area": 87.36,
    "price": 22800000,
    "access": "阪神電鉄阪神なんば線「福」徒歩9分",
    "nearStation": [
      {
        "name": "福",
        "min": 9,
        "passenger": 13123,
        "geometry": { "lng": 135.442735, "lat": 34.699825000000004 }
      }
    ],
    "info": { "buildingCoverageRatio": 80, "floorAreaRatio": 200 },
    "rentPrice": 51100
  },
  {
    "title": "兵庫県西宮市鳴尾町２",
    "url": "https://suumo.jp/tochi/__JJ_JJ010FJ100_arz1060z2bsz1030z2ncz170488410.html",
    "image": "https://img01.suumo.com/jj/resizeImage?src=gazo%2Fbukken%2F060%2FN010000%2Fimg%2F410%2F70488410%2F70488410_0012.jpg&w=132&h=99",
    "agent": "suumo",
    "prefecture": "hyogo",
    "area": 140.4,
    "price": 42800000,
    "access": "阪神本線「鳴尾・武庫川女子大前」徒歩10分",
    "nearStation": [
      {
        "name": "鳴尾・武庫川女子大前",
        "min": 10,
        "passenger": 24746,
        "geometry": { "lng": 135.37071500000002, "lat": 34.71959 }
      }
    ],
    "info": { "buildingCoverageRatio": 60, "floorAreaRatio": 200 },
    "rentPrice": 52900
  },
  {
    "title": "兵庫県西宮市甲陽園山王町",
    "url": "https://suumo.jp/tochi/__JJ_JJ010FJ100_arz1060z2bsz1030z2ncz172095525.html",
    "image": "https://img01.suumo.com/jj/resizeImage?src=gazo%2Fbukken%2F060%2FN010000%2Fimg%2F525%2F72095525%2F72095525_0001.jpg&w=132&h=99",
    "agent": "suumo",
    "prefecture": "hyogo",
    "area": 347,
    "price": 22800000,
    "access": "阪急甲陽線「甲陽園」徒歩10分",
    "nearStation": [
      {
        "name": "甲陽園",
        "min": 10,
        "passenger": 9858,
        "geometry": { "lng": 135.33022499999998, "lat": 34.760755 }
      }
    ],
    "info": { "buildingCoverageRatio": 40, "floorAreaRatio": 100 },
    "rentPrice": 49400
  },
  {
    "title": "兵庫県姫路市勝原区宮田",
    "url": "https://suumo.jp/tochi/__JJ_JJ010FJ100_arz1060z2bsz1030z2ncz170787466.html",
    "image": "https://img01.suumo.com/jj/resizeImage?src=gazo%2Fbukken%2F060%2FN010000%2Fimg%2F466%2F70787466%2F70787466_0008.jpg&w=132&h=99",
    "agent": "suumo",
    "prefecture": "hyogo",
    "area": 166.4,
    "price": 9800000,
    "access": "ＪＲ山陽本線「網干」徒歩15分",
    "nearStation": [
      {
        "name": "網干",
        "min": 15,
        "passenger": 15518,
        "geometry": { "lng": 134.58476000000002, "lat": 34.814245 }
      }
    ],
    "info": { "buildingCoverageRatio": 60, "floorAreaRatio": 150 },
    "rentPrice": 50300
  },
  {
    "title": "埼玉県さいたま市浦和区常盤３",
    "url": "https://suumo.jp/tochi/__JJ_JJ010FJ100_arz1030z2bsz1030z2ncz170955834.html",
    "image": "https://img01.suumo.com/jj/resizeImage?src=gazo%2Fbukken%2F030%2FN010000%2Fimg%2F834%2F70955834%2F70955834_0002.jpg&w=132&h=99",
    "agent": "suumo",
    "prefecture": "saitama",
    "area": 105.63,
    "price": 77800000,
    "access": "ＪＲ京浜東北線「浦和」徒歩16分",
    "nearStation": [
      {
        "name": "浦和",
        "min": 16,
        "passenger": 190128,
        "geometry": { "lng": 139.657145, "lat": 35.858565 }
      }
    ],
    "info": { "buildingCoverageRatio": 60, "floorAreaRatio": 200 },
    "rentPrice": 65100
  },
  {
    "title": "埼玉県熊谷市新堀",
    "url": "https://suumo.jp/tochi/__JJ_JJ010FJ100_arz1030z2bsz1030z2ncz171376188.html",
    "image": "https://img01.suumo.com/jj/resizeImage?src=gazo%2Fbukken%2F030%2FN010000%2Fimg%2F188%2F71376188%2F71376188_0007.jpg&w=132&h=99",
    "agent": "suumo",
    "prefecture": "saitama",
    "area": 190.55,
    "price": 15800000,
    "access": "ＪＲ高崎線「籠原」徒歩8分",
    "nearStation": [
      {
        "name": "籠原",
        "min": 8,
        "passenger": 30154,
        "geometry": { "lng": 139.33026, "lat": 36.17442 }
      }
    ],
    "info": { "buildingCoverageRatio": 60, "floorAreaRatio": 200 },
    "rentPrice": 54255
  },
  {
    "title": "埼玉県蕨市錦町６",
    "url": "https://suumo.jp/tochi/__JJ_JJ010FJ100_arz1030z2bsz1030z2ncz172054343.html",
    "image": "https://img01.suumo.com/jj/resizeImage?src=gazo%2Fbukken%2F030%2FN010000%2Fimg%2F343%2F72054343%2F72054343_0001.jpg&w=132&h=99",
    "agent": "suumo",
    "prefecture": "saitama",
    "area": 183,
    "price": 93800000,
    "access": "ＪＲ埼京線「北戸田」徒歩8分",
    "nearStation": [
      {
        "name": "北戸田",
        "min": 8,
        "passenger": 44040,
        "geometry": { "lng": 139.66144500000001, "lat": 35.826755000000006 }
      }
    ],
    "info": { "buildingCoverageRatio": 60, "floorAreaRatio": 200 },
    "rentPrice": 66644
  },
  {
    "title": "埼玉県さいたま市南区南浦和１",
    "url": "https://suumo.jp/tochi/__JJ_JJ010FJ100_arz1030z2bsz1030z2ncz172130780.html",
    "image": "https://img01.suumo.com/jj/resizeImage?src=gazo%2Fbukken%2F030%2FN010000%2Fimg%2F780%2F72130780%2F72130780_0001.jpg&w=132&h=99",
    "agent": "suumo",
    "prefecture": "saitama",
    "area": 114.17,
    "price": 74500000,
    "access": "ＪＲ京浜東北線「南浦和」徒歩9分",
    "nearStation": [
      {
        "name": "南浦和",
        "min": 9,
        "passenger": 120778,
        "geometry": { "lng": 139.66894000000002, "lat": 35.847584999999995 }
      }
    ],
    "info": { "buildingCoverageRatio": 60, "floorAreaRatio": 200 },
    "rentPrice": 70990
  },
  {
    "title": "京都府京都市西京区山田六ノ坪町",
    "url": "https://suumo.jp/tochi/__JJ_JJ010FJ100_arz1060z2bsz1030z2ncz198330901.html",
    "image": "https://img01.suumo.com/jj/resizeImage?src=gazo%2Fbukken%2F060%2FN010000%2Fimg%2F901%2F98330901%2F98330901_0001.jpg&w=132&h=99",
    "agent": "suumo",
    "prefecture": "kyotoMetro",
    "area": 172.71,
    "price": 47800000,
    "access": "阪急嵐山線「上桂」徒歩14分",
    "nearStation": [
      {
        "name": "上桂",
        "min": 14,
        "passenger": 7983,
        "geometry": { "lng": 135.69621, "lat": 34.990025 }
      }
    ],
    "info": { "buildingCoverageRatio": 80, "floorAreaRatio": 300 },
    "rentPrice": 45000
  },
  {
    "title": "京都府京都市西京区川島東代町",
    "url": "https://suumo.jp/tochi/__JJ_JJ010FJ100_arz1060z2bsz1030z2ncz172139625.html",
    "image": "https://img01.suumo.com/jj/resizeImage?src=gazo%2Fbukken%2F060%2FN010000%2Fimg%2F625%2F72139625%2F72139625_0001.jpg&w=132&h=99",
    "agent": "suumo",
    "prefecture": "kyotoMetro",
    "area": 239.45,
    "price": 97400000,
    "access": "阪急京都線「桂」徒歩7分",
    "nearStation": [
      {
        "name": "桂",
        "min": 7,
        "passenger": 45103,
        "geometry": { "lng": 135.70315499999998, "lat": 34.97938 }
      }
    ],
    "info": { "buildingCoverageRatio": 60, "floorAreaRatio": 200 },
    "rentPrice": 50100
  },
  {
    "title": "京都府京都市伏見区西大文字町",
    "url": "https://suumo.jp/tochi/__JJ_JJ010FJ100_arz1060z2bsz1030z2ncz172139623.html",
    "image": "https://img01.suumo.com/jj/resizeImage?src=gazo%2Fbukken%2F060%2FN010000%2Fimg%2F623%2F72139623%2F72139623_0001.jpg&w=132&h=99",
    "agent": "suumo",
    "prefecture": "kyotoMetro",
    "area": 223.86,
    "price": 50700000,
    "access": "京阪本線「伏見桃山」徒歩15分",
    "nearStation": [
      {
        "name": "伏見桃山",
        "min": 15,
        "passenger": 10469,
        "geometry": { "lng": 135.76436, "lat": 34.932505 }
      }
    ],
    "info": { "buildingCoverageRatio": 60, "floorAreaRatio": 200 },
    "rentPrice": 52200
  },
  {
    "title": "京都府京都市西京区桂木ノ下町",
    "url": "https://suumo.jp/tochi/__JJ_JJ010FJ100_arz1060z2bsz1030z2ncz172144055.html",
    "image": "https://img01.suumo.com/jj/resizeImage?src=gazo%2Fbukken%2F060%2FN010000%2Fimg%2F055%2F72144055%2F72144055_0011.jpg&w=132&h=99",
    "agent": "suumo",
    "prefecture": "kyotoMetro",
    "area": 112.74,
    "price": 47070000,
    "access": "阪急京都線「桂」徒歩5分",
    "nearStation": [
      {
        "name": "桂",
        "min": 5,
        "passenger": 45103,
        "geometry": { "lng": 135.70315499999998, "lat": 34.97938 }
      }
    ],
    "info": { "buildingCoverageRatio": 60, "floorAreaRatio": 200 },
    "rentPrice": 50100
  },
  {
    "title": "兵庫県神戸市灘区天城通１",
    "url": "https://suumo.jp/tochi/__JJ_JJ010FJ100_arz1060z2bsz1030z2ncz172067586.html",
    "image": "https://img01.suumo.com/jj/resizeImage?src=gazo%2Fbukken%2F060%2FN010000%2Fimg%2F586%2F72067586%2F72067586_0011.jpg&w=132&h=99",
    "agent": "suumo",
    "prefecture": "hyogoMetro",
    "area": 100.01,
    "price": 41800000,
    "access": "阪急神戸線「王子公園」徒歩13分",
    "nearStation": [
      {
        "name": "王子公園",
        "min": 13,
        "passenger": 17996,
        "geometry": { "lng": 135.21864, "lat": 34.71034 }
      }
    ],
    "info": { "buildingCoverageRatio": 60, "floorAreaRatio": 200 },
    "rentPrice": 51700
  },
  {
    "title": "兵庫県神戸市垂水区歌敷山３",
    "url": "https://suumo.jp/tochi/__JJ_JJ010FJ100_arz1060z2bsz1030z2ncz172173518.html",
    "image": "https://img01.suumo.com/jj/resizeImage?src=gazo%2Fbukken%2F060%2FN010000%2Fimg%2F518%2F72173518%2F72173518_0001.jpg&w=132&h=99",
    "agent": "suumo",
    "prefecture": "hyogoMetro",
    "area": 211.46,
    "price": 38000000,
    "access": "山陽電鉄本線「霞ケ丘」徒歩11分",
    "nearStation": [
      {
        "name": "霞ケ丘",
        "min": 11,
        "passenger": 0,
        "geometry": { "lng": 0, "lat": 0 }
      }
    ],
    "info": { "buildingCoverageRatio": 60, "floorAreaRatio": 150 },
    "rentPrice": 45000
  },
  {
    "title": "宮城県仙台市青葉区東照宮１",
    "url": "https://suumo.jp/tochi/__JJ_JJ010FJ100_arz1020z2bsz1030z2ncz172091298.html",
    "image": "https://img01.suumo.com/jj/resizeImage?src=gazo%2Fbukken%2F020%2FN010000%2Fimg%2F298%2F72091298%2F72091298_0001.jpg&w=132&h=99",
    "agent": "suumo",
    "prefecture": "sendai",
    "area": 113.17,
    "price": 25900000,
    "access": "ＪＲ仙山線「東照宮」徒歩6分",
    "nearStation": [
      {
        "name": "東照宮",
        "min": 6,
        "passenger": 6892,
        "geometry": { "lng": 140.887385, "lat": 38.27707 }
      }
    ],
    "info": { "buildingCoverageRatio": 60, "floorAreaRatio": 200 },
    "rentPrice": 47700
  },
  {
    "title": "宮城県仙台市宮城野区東仙台６",
    "url": "https://suumo.jp/tochi/__JJ_JJ010FJ100_arz1020z2bsz1030z2ncz172172892.html",
    "image": "https://img01.suumo.com/jj/resizeImage?src=gazo%2Fbukken%2F020%2FN010000%2Fimg%2F892%2F72172892%2F72172892_0001.jpg&w=132&h=99",
    "agent": "suumo",
    "prefecture": "sendai",
    "area": 197.52,
    "price": 20300000,
    "access": "ＪＲ東北本線「東仙台」徒歩11分",
    "nearStation": [
      {
        "name": "東仙台",
        "min": 11,
        "passenger": 7256,
        "geometry": { "lng": 140.920115, "lat": 38.276520000000005 }
      }
    ],
    "info": { "buildingCoverageRatio": 60, "floorAreaRatio": 200 },
    "rentPrice": 48200
  },
  {
    "title": "広島県広島市中区江波栄町",
    "url": "https://suumo.jp/tochi/__JJ_JJ010FJ100_arz1080z2bsz1030z2ncz171955548.html",
    "image": "https://img01.suumo.com/jj/resizeImage?src=gazo%2Fbukken%2F080%2FN010000%2Fimg%2F548%2F71955548%2F71955548_0010.jpg&w=132&h=99",
    "agent": "suumo",
    "prefecture": "hiroshima",
    "area": 262.77,
    "price": 48000000,
    "access": "バス「江波栄町」徒歩2分",
    "nearStation": [
      {
        "name": "江波栄町",
        "min": 2,
        "passenger": 0,
        "geometry": { "lng": 0, "lat": 0 }
      }
    ],
    "info": { "buildingCoverageRatio": 60, "floorAreaRatio": 200 },
    "rentPrice": 45000
  },
  {
    "title": "広島県広島市中区江波栄町3-8",
    "url": "https://suumo.jp/tochi/__JJ_JJ010FJ100_arz1080z2bsz1030z2ncz171951263.html",
    "image": "https://img01.suumo.com/jj/resizeImage?src=gazo%2Fbukken%2F080%2FN010000%2Fimg%2F263%2F71951263%2F71951263_0006.jpg&w=132&h=99",
    "agent": "suumo",
    "prefecture": "hiroshima",
    "area": 262.77,
    "price": 48000000,
    "access": "広島電鉄江波線「江波」徒歩14分",
    "nearStation": [
      {
        "name": "江波",
        "min": 14,
        "passenger": 1703,
        "geometry": { "lng": 132.435815, "lat": 34.372209999999995 }
      }
    ],
    "info": { "buildingCoverageRatio": 60, "floorAreaRatio": 200 },
    "rentPrice": 51000
  },
  {
    "title": "広島県広島市安佐南区川内１",
    "url": "https://suumo.jp/tochi/__JJ_JJ010FJ100_arz1080z2bsz1030z2ncz172172533.html",
    "image": "https://img01.suumo.com/jj/resizeImage?src=gazo%2Fbukken%2F080%2FN010000%2Fimg%2F533%2F72172533%2F72172533_0001.jpg&w=132&h=99",
    "agent": "suumo",
    "prefecture": "hiroshima",
    "area": 145.71,
    "price": 33800000,
    "access": "広島高速交通アストラムライン「中筋」徒歩12分",
    "nearStation": [
      {
        "name": "中筋",
        "min": 12,
        "passenger": 8281,
        "geometry": { "lng": 132.47694, "lat": 34.451765 }
      }
    ],
    "info": { "buildingCoverageRatio": 60, "floorAreaRatio": 200 },
    "rentPrice": 41000
  },
  {
    "title": "北海道札幌市中央区南七条西２６",
    "url": "https://suumo.jp/tochi/__JJ_JJ010FJ100_arz1010z2bsz1030z2ncz171824433.html",
    "image": "https://img01.suumo.com/jj/resizeImage?src=gazo%2Fbukken%2F010%2FN010000%2Fimg%2F433%2F71824433%2F71824433_0001.jpg&w=132&h=99",
    "agent": "suumo",
    "prefecture": "sapporo",
    "area": 198.01,
    "price": 48800000,
    "access": "地下鉄東西線「円山公園」徒歩11分",
    "nearStation": [
      {
        "name": "円山公園",
        "min": 11,
        "passenger": 30504,
        "geometry": { "lng": 141.31951500000002, "lat": 43.055735 }
      }
    ],
    "info": { "buildingCoverageRatio": 80, "floorAreaRatio": 300 },
    "rentPrice": 40000
  },
  {
    "title": "北海道札幌市東区北三十四条東８",
    "url": "https://suumo.jp/tochi/__JJ_JJ010FJ100_arz1010z2bsz1030z2ncz170927878.html",
    "image": "https://img01.suumo.com/jj/resizeImage?src=gazo%2Fbukken%2F010%2FN010000%2Fimg%2F878%2F70927878%2F70927878_0001.jpg&w=132&h=99",
    "agent": "suumo",
    "prefecture": "sapporo",
    "area": 293.49,
    "price": 45000000,
    "access": "地下鉄東豊線「新道東」徒歩11分",
    "nearStation": [
      {
        "name": "新道東",
        "min": 11,
        "passenger": 15954,
        "geometry": { "lng": 141.36914000000002, "lat": 43.104870000000005 }
      }
    ],
    "info": { "buildingCoverageRatio": 60, "floorAreaRatio": 200 },
    "rentPrice": 32600
  },
  {
    "title": "北海道札幌市東区北二十八条東１９",
    "url": "https://suumo.jp/tochi/__JJ_JJ010FJ100_arz1010z2bsz1030z2ncz171706341.html",
    "image": "https://img01.suumo.com/jj/resizeImage?src=gazo%2Fbukken%2F010%2FN010000%2Fimg%2F341%2F71706341%2F71706341_0014.jpg&w=132&h=99",
    "agent": "suumo",
    "prefecture": "sapporo",
    "area": 216.8,
    "price": 35000000,
    "access": "地下鉄東豊線「元町」徒歩15分",
    "nearStation": [
      {
        "name": "元町",
        "min": 15,
        "passenger": 18724,
        "geometry": { "lng": 141.371785, "lat": 43.09404 }
      }
    ],
    "info": { "buildingCoverageRatio": 60, "floorAreaRatio": 200 },
    "rentPrice": 31700
  },
  {
    "title": "北海道札幌市東区北二十五条東２２",
    "url": "https://suumo.jp/tochi/__JJ_JJ010FJ100_arz1010z2bsz1030z2ncz171758069.html",
    "image": "https://img01.suumo.com/jj/resizeImage?src=gazo%2Fbukken%2F010%2FN010000%2Fimg%2F069%2F71758069%2F71758069_0001.jpg&w=132&h=99",
    "agent": "suumo",
    "prefecture": "sapporo",
    "area": 215.72,
    "price": 27500000,
    "access": "地下鉄東豊線「元町」徒歩15分",
    "nearStation": [
      {
        "name": "元町",
        "min": 15,
        "passenger": 18724,
        "geometry": { "lng": 141.371785, "lat": 43.09404 }
      }
    ],
    "info": { "buildingCoverageRatio": 60, "floorAreaRatio": 200 },
    "rentPrice": 31700
  },
  {
    "title": "北海道札幌市東区北十九条東１７",
    "url": "https://suumo.jp/tochi/__JJ_JJ010FJ100_arz1010z2bsz1030z2ncz172145940.html",
    "image": "https://img01.suumo.com/jj/resizeImage?src=gazo%2Fbukken%2F010%2FN010000%2Fimg%2F940%2F72145940%2F72145940_0001.jpg&w=132&h=99",
    "agent": "suumo",
    "prefecture": "sapporo",
    "area": 231.69,
    "price": 31500000,
    "access": "地下鉄東豊線「環状通東」徒歩11分",
    "nearStation": [
      {
        "name": "環状通東",
        "min": 11,
        "passenger": 17896,
        "geometry": { "lng": 141.374425, "lat": 43.08238 }
      }
    ],
    "info": { "buildingCoverageRatio": 60, "floorAreaRatio": 200 },
    "rentPrice": 33300
  },
  {
    "title": "北海道札幌市白石区平和通７丁目北129",
    "url": "https://suumo.jp/tochi/__JJ_JJ010FJ100_arz1010z2bsz1030z2ncz172144300.html",
    "image": "https://img01.suumo.com/jj/resizeImage?src=gazo%2Fbukken%2F010%2FN010000%2Fimg%2F300%2F72144300%2F72144300_0047.jpg&w=132&h=99",
    "agent": "suumo",
    "prefecture": "sapporo",
    "area": 254,
    "price": 16800000,
    "access": "ＪＲ函館本線「白石」徒歩12分",
    "nearStation": [
      {
        "name": "白石",
        "min": 12,
        "passenger": 45162,
        "geometry": { "lng": 141.41406999999998, "lat": 43.05476 }
      }
    ],
    "info": { "buildingCoverageRatio": 60, "floorAreaRatio": 200 },
    "rentPrice": 35100
  }
]
